[
  {
    "country": "US",
    "state_abbr": "NC",
    "state_name": "North Carolina",
    "name": "Currituck County",
    "osm_type": "relation",
    "osm_id": 1232243,
    "admin_level": "6",
    "level_name": "Counties/County-equivalents",
    "wikidata": "Q511761",
    "fips": null,
    "alt_name": null,
    "short_name": null,
    "official_name": null
  },
  {
    "country": "US",
    "state_abbr": "NC",
    "state_name": "North Carolina",
    "name": "Dare County",
    "osm_type": "relation",
    "osm_id": 1232267,
    "admin_level": "6",
    "level_name": "Counties/County-equivalents",
    "wikidata": "Q295787",
    "fips": null,
    "alt_name": null,
    "short_name": null,
    "official_name": null
  },
  {
    "country": "US",
    "state_abbr": "NC",
    "state_name": "North Carolina",
    "name": "Hyde County",
    "osm_type": "relation",
    "osm_id": 1236353,
    "admin_level": "6",
    "level_name": "Counties/County-equivalents",
    "wikidata": "Q511659",
    "fips": null,
    "alt_name": null,
    "short_name": null,
    "official_name": null
  },
  {
    "country": "US",
    "state_abbr": "NC",
    "state_name": "North Carolina",
    "name": "Hertford County",
    "osm_type": "relation",
    "osm_id": 1242000,
    "admin_level": "6",
    "level_name": "Counties/County-equivalents",
    "wikidata": "Q751202",
    "fips": null,
    "alt_name": null,
    "short_name": null,
    "official_name": null
  },
  {
    "country": "US",
    "state_abbr": "NC",
    "state_name": "North Carolina",
    "name": "Perquimans County",
    "osm_type": "relation",
    "osm_id": 1242001,
    "admin_level": "6",
    "level_name": "Counties/County-equivalents",
    "wikidata": "Q201014",
    "fips": null,
    "alt_name": null,
    "short_name": null,
    "official_name": null
  },
  {
    "country": "US",
    "state_abbr": "NC",
    "state_name": "North Carolina",
    "name": "Camden County",
    "osm_type": "relation",
    "osm_id": 1242002,
    "admin_level": "6",
    "level_name": "Counties/County-equivalents",
    "wikidata": "Q504294",
    "fips": null,
    "alt_name": null,
    "short_name": null,
    "official_name": null
  },
  {
    "country": "US",
    "state_abbr": "NC",
    "state_name": "North Carolina",
    "name": "Gates County",
    "osm_type": "relation",
    "osm_id": 1242003,
    "admin_level": "6",
    "level_name": "Counties/County-equivalents",
    "wikidata": "Q509838",
    "fips": null,
    "alt_name": null,
    "short_name": null,
    "official_name": null
  },
  {
    "country": "US",
    "state_abbr": "NC",
    "state_name": "North Carolina",
    "name": "Pasquotank County",
    "osm_type": "relation",
    "osm_id": 1242004,
    "admin_level": "6",
    "level_name": "Counties/County-equivalents",
    "wikidata": "Q507438",
    "fips": null,
    "alt_name": null,
    "short_name": null,
    "official_name": null
  },
  {
    "country": "US",
    "state_abbr": "NC",
    "state_name": "North Carolina",
    "name": "Bertie County",
    "osm_type": "relation",
    "osm_id": 1242005,
    "admin_level": "6",
    "level_name": "Counties/County-equivalents",
    "wikidata": "Q504335",
    "fips": null,
    "alt_name": null,
    "short_name": null,
    "official_name": null
  },
  {
    "country": "US",
    "state_abbr": "NC",
    "state_name": "North Carolina",
    "name": "Chowan County",
    "osm_type": "relation",
    "osm_id": 1242006,
    "admin_level": "6",
    "level_name": "Counties/County-equivalents",
    "wikidata": "Q943772",
    "fips": null,
    "alt_name": null,
    "short_name": null,
    "official_name": null
  },
  {
    "country": "US",
    "state_abbr": "NC",
    "state_name": "North Carolina",
    "name": "Alamance County",
    "osm_type": "relation",
    "osm_id": 2528669,
    "admin_level": "6",
    "level_name": "Counties/County-equivalents",
    "wikidata": "Q504397",
    "fips": null,
    "alt_name": null,
    "short_name": null,
    "official_name": null
  },
  {
    "country": "US",
    "state_abbr": "NC",
    "state_name": "North Carolina",
    "name": "Alexander County",
    "osm_type": "relation",
    "osm_id": 2528670,
    "admin_level": "6",
    "level_name": "Counties/County-equivalents",
    "wikidata": "Q491584",
    "fips": null,
    "alt_name": null,
    "short_name": null,
    "official_name": null
  },
  {
    "country": "US",
    "state_abbr": "NC",
    "state_name": "North Carolina",
    "name": "Alleghany County",
    "osm_type": "relation",
    "osm_id": 2528671,
    "admin_level": "6",
    "level_name": "Counties/County-equivalents",
    "wikidata": "Q497899",
    "fips": null,
    "alt_name": null,
    "short_name": null,
    "official_name": null
  },
  {
    "country": "US",
    "state_abbr": "NC",
    "state_name": "North Carolina",
    "name": "Anson County",
    "osm_type": "relation",
    "osm_id": 2528672,
    "admin_level": "6",
    "level_name": "Counties/County-equivalents",
    "wikidata": "Q497830",
    "fips": null,
    "alt_name": null,
    "short_name": null,
    "official_name": null
  },
  {
    "country": "US",
    "state_abbr": "NC",
    "state_name": "North Carolina",
    "name": "Ashe County",
    "osm_type": "relation",
    "osm_id": 2528673,
    "admin_level": "6",
    "level_name": "Counties/County-equivalents",
    "wikidata": "Q491626",
    "fips": null,
    "alt_name": null,
    "short_name": null,
    "official_name": null
  },
  {
    "country": "US",
    "state_abbr": "NC",
    "state_name": "North Carolina",
    "name": "Avery County",
    "osm_type": "relation",
    "osm_id": 2528674,
    "admin_level": "6",
    "level_name": "Counties/County-equivalents",
    "wikidata": "Q497804",
    "fips": null,
    "alt_name": null,
    "short_name": null,
    "official_name": null
  },
  {
    "country": "US",
    "state_abbr": "NC",
    "state_name": "North Carolina",
    "name": "Beaufort County",
    "osm_type": "relation",
    "osm_id": 2528675,
    "admin_level": "6",
    "level_name": "Counties/County-equivalents",
    "wikidata": "Q484639",
    "fips": null,
    "alt_name": null,
    "short_name": null,
    "official_name": null
  },
  {
    "country": "US",
    "state_abbr": "NC",
    "state_name": "North Carolina",
    "name": "Bladen County",
    "osm_type": "relation",
    "osm_id": 2528676,
    "admin_level": "6",
    "level_name": "Counties/County-equivalents",
    "wikidata": "Q504403",
    "fips": null,
    "alt_name": null,
    "short_name": null,
    "official_name": null
  },
  {
    "country": "US",
    "state_abbr": "NC",
    "state_name": "North Carolina",
    "name": "Brunswick County",
    "osm_type": "relation",
    "osm_id": 2528677,
    "admin_level": "6",
    "level_name": "Counties/County-equivalents",
    "wikidata": "Q504329",
    "fips": null,
    "alt_name": null,
    "short_name": null,
    "official_name": null
  },
  {
    "country": "US",
    "state_abbr": "NC",
    "state_name": "North Carolina",
    "name": "Buncombe County",
    "osm_type": "relation",
    "osm_id": 2528678,
    "admin_level": "6",
    "level_name": "Counties/County-equivalents",
    "wikidata": "Q504360",
    "fips": null,
    "alt_name": null,
    "short_name": null,
    "official_name": null
  },
  {
    "country": "US",
    "state_abbr": "NC",
    "state_name": "North Carolina",
    "name": "Burke County",
    "osm_type": "relation",
    "osm_id": 2528679,
    "admin_level": "6",
    "level_name": "Counties/County-equivalents",
    "wikidata": "Q504366",
    "fips": null,
    "alt_name": null,
    "short_name": null,
    "official_name": null
  },
  {
    "country": "US",
    "state_abbr": "NC",
    "state_name": "North Carolina",
    "name": "Cabarrus County",
    "osm_type": "relation",
    "osm_id": 2528680,
    "admin_level": "6",
    "level_name": "Counties/County-equivalents",
    "wikidata": "Q176307",
    "fips": null,
    "alt_name": null,
    "short_name": null,
    "official_name": null
  },
  {
    "country": "US",
    "state_abbr": "NC",
    "state_name": "North Carolina",
    "name": "Caldwell County",
    "osm_type": "relation",
    "osm_id": 2528681,
    "admin_level": "6",
    "level_name": "Counties/County-equivalents",
    "wikidata": "Q497908",
    "fips": null,
    "alt_name": null,
    "short_name": null,
    "official_name": null
  },
  {
    "country": "US",
    "state_abbr": "NC",
    "state_name": "North Carolina",
    "name": "Carteret County",
    "osm_type": "relation",
    "osm_id": 2528682,
    "admin_level": "6",
    "level_name": "Counties/County-equivalents",
    "wikidata": "Q497817",
    "fips": null,
    "alt_name": null,
    "short_name": null,
    "official_name": null
  },
  {
    "country": "US",
    "state_abbr": "NC",
    "state_name": "North Carolina",
    "name": "Caswell County",
    "osm_type": "relation",
    "osm_id": 2528683,
    "admin_level": "6",
    "level_name": "Counties/County-equivalents",
    "wikidata": "Q504428",
    "fips": null,
    "alt_name": null,
    "short_name": null,
    "official_name": null
  },
  {
    "country": "US",
    "state_abbr": "NC",
    "state_name": "North Carolina",
    "name": "Catawba County",
    "osm_type": "relation",
    "osm_id": 2528684,
    "admin_level": "6",
    "level_name": "Counties/County-equivalents",
    "wikidata": "Q502483",
    "fips": null,
    "alt_name": null,
    "short_name": null,
    "official_name": null
  },
  {
    "country": "US",
    "state_abbr": "NC",
    "state_name": "North Carolina",
    "name": "Chatham County",
    "osm_type": "relation",
    "osm_id": 2528685,
    "admin_level": "6",
    "level_name": "Counties/County-equivalents",
    "wikidata": "Q504410",
    "fips": null,
    "alt_name": null,
    "short_name": null,
    "official_name": null
  },
  {
    "country": "US",
    "state_abbr": "NC",
    "state_name": "North Carolina",
    "name": "Cherokee County",
    "osm_type": "relation",
    "osm_id": 2528686,
    "admin_level": "6",
    "level_name": "Counties/County-equivalents",
    "wikidata": "Q484664",
    "fips": null,
    "alt_name": null,
    "short_name": null,
    "official_name": null
  },
  {
    "country": "US",
    "state_abbr": "NC",
    "state_name": "North Carolina",
    "name": "Clay County",
    "osm_type": "relation",
    "osm_id": 2528687,
    "admin_level": "6",
    "level_name": "Counties/County-equivalents",
    "wikidata": "Q502516",
    "fips": null,
    "alt_name": null,
    "short_name": null,
    "official_name": null
  },
  {
    "country": "US",
    "state_abbr": "NC",
    "state_name": "North Carolina",
    "name": "Cleveland County",
    "osm_type": "relation",
    "osm_id": 2528688,
    "admin_level": "6",
    "level_name": "Counties/County-equivalents",
    "wikidata": "Q511691",
    "fips": null,
    "alt_name": null,
    "short_name": null,
    "official_name": null
  },
  {
    "country": "US",
    "state_abbr": "NC",
    "state_name": "North Carolina",
    "name": "Columbus County",
    "osm_type": "relation",
    "osm_id": 2528689,
    "admin_level": "6",
    "level_name": "Counties/County-equivalents",
    "wikidata": "Q509813",
    "fips": null,
    "alt_name": null,
    "short_name": null,
    "official_name": null
  },
  {
    "country": "US",
    "state_abbr": "NC",
    "state_name": "North Carolina",
    "name": "Craven County",
    "osm_type": "relation",
    "osm_id": 2528690,
    "admin_level": "6",
    "level_name": "Counties/County-equivalents",
    "wikidata": "Q529958",
    "fips": null,
    "alt_name": null,
    "short_name": null,
    "official_name": null
  },
  {
    "country": "US",
    "state_abbr": "NC",
    "state_name": "North Carolina",
    "name": "Cumberland County",
    "osm_type": "relation",
    "osm_id": 2528692,
    "admin_level": "6",
    "level_name": "Counties/County-equivalents",
    "wikidata": "Q511834",
    "fips": null,
    "alt_name": null,
    "short_name": null,
    "official_name": null
  },
  {
    "country": "US",
    "state_abbr": "NC",
    "state_name": "North Carolina",
    "name": "Davidson County",
    "osm_type": "relation",
    "osm_id": 2528693,
    "admin_level": "6",
    "level_name": "Counties/County-equivalents",
    "wikidata": "Q511713",
    "fips": null,
    "alt_name": null,
    "short_name": null,
    "official_name": null
  },
  {
    "country": "US",
    "state_abbr": "NC",
    "state_name": "North Carolina",
    "name": "Davie County",
    "osm_type": "relation",
    "osm_id": 2528694,
    "admin_level": "6",
    "level_name": "Counties/County-equivalents",
    "wikidata": "Q509786",
    "fips": null,
    "alt_name": null,
    "short_name": null,
    "official_name": null
  },
  {
    "country": "US",
    "state_abbr": "NC",
    "state_name": "North Carolina",
    "name": "Duplin County",
    "osm_type": "relation",
    "osm_id": 2528695,
    "admin_level": "6",
    "level_name": "Counties/County-equivalents",
    "wikidata": "Q511788",
    "fips": null,
    "alt_name": null,
    "short_name": null,
    "official_name": null
  },
  {
    "country": "US",
    "state_abbr": "NC",
    "state_name": "North Carolina",
    "name": "Durham County",
    "osm_type": "relation",
    "osm_id": 2528696,
    "admin_level": "6",
    "level_name": "Counties/County-equivalents",
    "wikidata": "Q428298",
    "fips": null,
    "alt_name": null,
    "short_name": null,
    "official_name": null
  },
  {
    "country": "US",
    "state_abbr": "NC",
    "state_name": "North Carolina",
    "name": "Wake County",
    "osm_type": "relation",
    "osm_id": 2528697,
    "admin_level": "6",
    "level_name": "Counties/County-equivalents",
    "wikidata": "Q506215",
    "fips": null,
    "alt_name": null,
    "short_name": null,
    "official_name": null
  },
  {
    "country": "US",
    "state_abbr": "NC",
    "state_name": "North Carolina",
    "name": "Edgecombe County",
    "osm_type": "relation",
    "osm_id": 2528698,
    "admin_level": "6",
    "level_name": "Counties/County-equivalents",
    "wikidata": "Q118127",
    "fips": null,
    "alt_name": null,
    "short_name": null,
    "official_name": null
  },
  {
    "country": "US",
    "state_abbr": "NC",
    "state_name": "North Carolina",
    "name": "Forsyth County",
    "osm_type": "relation",
    "osm_id": 2528699,
    "admin_level": "6",
    "level_name": "Counties/County-equivalents",
    "wikidata": "Q509926",
    "fips": null,
    "alt_name": null,
    "short_name": null,
    "official_name": null
  },
  {
    "country": "US",
    "state_abbr": "NC",
    "state_name": "North Carolina",
    "name": "Franklin County",
    "osm_type": "relation",
    "osm_id": 2528700,
    "admin_level": "6",
    "level_name": "Counties/County-equivalents",
    "wikidata": "Q502526",
    "fips": null,
    "alt_name": null,
    "short_name": null,
    "official_name": null
  },
  {
    "country": "US",
    "state_abbr": "NC",
    "state_name": "North Carolina",
    "name": "Gaston County",
    "osm_type": "relation",
    "osm_id": 2528701,
    "admin_level": "6",
    "level_name": "Counties/County-equivalents",
    "wikidata": "Q511849",
    "fips": null,
    "alt_name": null,
    "short_name": null,
    "official_name": null
  },
  {
    "country": "US",
    "state_abbr": "NC",
    "state_name": "North Carolina",
    "name": "Graham County",
    "osm_type": "relation",
    "osm_id": 2528702,
    "admin_level": "6",
    "level_name": "Counties/County-equivalents",
    "wikidata": "Q374968",
    "fips": null,
    "alt_name": null,
    "short_name": null,
    "official_name": null
  },
  {
    "country": "US",
    "state_abbr": "NC",
    "state_name": "North Carolina",
    "name": "Granville County",
    "osm_type": "relation",
    "osm_id": 2528703,
    "admin_level": "6",
    "level_name": "Counties/County-equivalents",
    "wikidata": "Q502503",
    "fips": null,
    "alt_name": null,
    "short_name": null,
    "official_name": null
  },
  {
    "country": "US",
    "state_abbr": "NC",
    "state_name": "North Carolina",
    "name": "Greene County",
    "osm_type": "relation",
    "osm_id": 2528704,
    "admin_level": "6",
    "level_name": "Counties/County-equivalents",
    "wikidata": "Q511772",
    "fips": null,
    "alt_name": null,
    "short_name": null,
    "official_name": null
  },
  {
    "country": "US",
    "state_abbr": "NC",
    "state_name": "North Carolina",
    "name": "Guilford County",
    "osm_type": "relation",
    "osm_id": 2528705,
    "admin_level": "6",
    "level_name": "Counties/County-equivalents",
    "wikidata": "Q502257",
    "fips": null,
    "alt_name": null,
    "short_name": null,
    "official_name": null
  },
  {
    "country": "US",
    "state_abbr": "NC",
    "state_name": "North Carolina",
    "name": "Halifax County",
    "osm_type": "relation",
    "osm_id": 2528706,
    "admin_level": "6",
    "level_name": "Counties/County-equivalents",
    "wikidata": "Q509910",
    "fips": null,
    "alt_name": null,
    "short_name": null,
    "official_name": null
  },
  {
    "country": "US",
    "state_abbr": "NC",
    "state_name": "North Carolina",
    "name": "Harnett County",
    "osm_type": "relation",
    "osm_id": 2528707,
    "admin_level": "6",
    "level_name": "Counties/County-equivalents",
    "wikidata": "Q497861",
    "fips": null,
    "alt_name": null,
    "short_name": null,
    "official_name": null
  },
  {
    "country": "US",
    "state_abbr": "NC",
    "state_name": "North Carolina",
    "name": "Haywood County",
    "osm_type": "relation",
    "osm_id": 2528708,
    "admin_level": "6",
    "level_name": "Counties/County-equivalents",
    "wikidata": "Q502496",
    "fips": null,
    "alt_name": null,
    "short_name": null,
    "official_name": null
  },
  {
    "country": "US",
    "state_abbr": "NC",
    "state_name": "North Carolina",
    "name": "Henderson County",
    "osm_type": "relation",
    "osm_id": 2528709,
    "admin_level": "6",
    "level_name": "Counties/County-equivalents",
    "wikidata": "Q511747",
    "fips": null,
    "alt_name": null,
    "short_name": null,
    "official_name": null
  },
  {
    "country": "US",
    "state_abbr": "NC",
    "state_name": "North Carolina",
    "name": "Hoke County",
    "osm_type": "relation",
    "osm_id": 2528710,
    "admin_level": "6",
    "level_name": "Counties/County-equivalents",
    "wikidata": "Q502507",
    "fips": null,
    "alt_name": null,
    "short_name": null,
    "official_name": null
  },
  {
    "country": "US",
    "state_abbr": "NC",
    "state_name": "North Carolina",
    "name": "Iredell County",
    "osm_type": "relation",
    "osm_id": 2528711,
    "admin_level": "6",
    "level_name": "Counties/County-equivalents",
    "wikidata": "Q502875",
    "fips": null,
    "alt_name": null,
    "short_name": null,
    "official_name": null
  },
  {
    "country": "US",
    "state_abbr": "NC",
    "state_name": "North Carolina",
    "name": "Jackson County",
    "osm_type": "relation",
    "osm_id": 2528712,
    "admin_level": "6",
    "level_name": "Counties/County-equivalents",
    "wikidata": "Q502521",
    "fips": null,
    "alt_name": null,
    "short_name": null,
    "official_name": null
  },
  {
    "country": "US",
    "state_abbr": "NC",
    "state_name": "North Carolina",
    "name": "Johnston County",
    "osm_type": "relation",
    "osm_id": 2528713,
    "admin_level": "6",
    "level_name": "Counties/County-equivalents",
    "wikidata": "Q497938",
    "fips": null,
    "alt_name": null,
    "short_name": null,
    "official_name": null
  },
  {
    "country": "US",
    "state_abbr": "NC",
    "state_name": "North Carolina",
    "name": "Jones County",
    "osm_type": "relation",
    "osm_id": 2528714,
    "admin_level": "6",
    "level_name": "Counties/County-equivalents",
    "wikidata": "Q502492",
    "fips": null,
    "alt_name": null,
    "short_name": null,
    "official_name": null
  },
  {
    "country": "US",
    "state_abbr": "NC",
    "state_name": "North Carolina",
    "name": "Lee County",
    "osm_type": "relation",
    "osm_id": 2528715,
    "admin_level": "6",
    "level_name": "Counties/County-equivalents",
    "wikidata": "Q507838",
    "fips": null,
    "alt_name": null,
    "short_name": null,
    "official_name": null
  },
  {
    "country": "US",
    "state_abbr": "NC",
    "state_name": "North Carolina",
    "name": "Lenoir County",
    "osm_type": "relation",
    "osm_id": 2528716,
    "admin_level": "6",
    "level_name": "Counties/County-equivalents",
    "wikidata": "Q507907",
    "fips": null,
    "alt_name": null,
    "short_name": null,
    "official_name": null
  },
  {
    "country": "US",
    "state_abbr": "NC",
    "state_name": "North Carolina",
    "name": "Lincoln County",
    "osm_type": "relation",
    "osm_id": 2528717,
    "admin_level": "6",
    "level_name": "Counties/County-equivalents",
    "wikidata": "Q507757",
    "fips": null,
    "alt_name": null,
    "short_name": null,
    "official_name": null
  },
  {
    "country": "US",
    "state_abbr": "NC",
    "state_name": "North Carolina",
    "name": "Macon County",
    "osm_type": "relation",
    "osm_id": 2528718,
    "admin_level": "6",
    "level_name": "Counties/County-equivalents",
    "wikidata": "Q507575",
    "fips": null,
    "alt_name": null,
    "short_name": null,
    "official_name": null
  },
  {
    "country": "US",
    "state_abbr": "NC",
    "state_name": "North Carolina",
    "name": "Madison County",
    "osm_type": "relation",
    "osm_id": 2528719,
    "admin_level": "6",
    "level_name": "Counties/County-equivalents",
    "wikidata": "Q506300",
    "fips": null,
    "alt_name": null,
    "short_name": null,
    "official_name": null
  },
  {
    "country": "US",
    "state_abbr": "NC",
    "state_name": "North Carolina",
    "name": "Martin County",
    "osm_type": "relation",
    "osm_id": 2528720,
    "admin_level": "6",
    "level_name": "Counties/County-equivalents",
    "wikidata": "Q505359",
    "fips": null,
    "alt_name": null,
    "short_name": null,
    "official_name": null
  },
  {
    "country": "US",
    "state_abbr": "NC",
    "state_name": "North Carolina",
    "name": "McDowell County",
    "osm_type": "relation",
    "osm_id": 2528721,
    "admin_level": "6",
    "level_name": "Counties/County-equivalents",
    "wikidata": "Q507811",
    "fips": null,
    "alt_name": null,
    "short_name": null,
    "official_name": null
  },
  {
    "country": "US",
    "state_abbr": "NC",
    "state_name": "North Carolina",
    "name": "Mecklenburg County",
    "osm_type": "relation",
    "osm_id": 2528722,
    "admin_level": "6",
    "level_name": "Counties/County-equivalents",
    "wikidata": "Q507770",
    "fips": null,
    "alt_name": null,
    "short_name": null,
    "official_name": null
  },
  {
    "country": "US",
    "state_abbr": "NC",
    "state_name": "North Carolina",
    "name": "Mitchell County",
    "osm_type": "relation",
    "osm_id": 2528723,
    "admin_level": "6",
    "level_name": "Counties/County-equivalents",
    "wikidata": "Q506337",
    "fips": null,
    "alt_name": null,
    "short_name": null,
    "official_name": null
  },
  {
    "country": "US",
    "state_abbr": "NC",
    "state_name": "North Carolina",
    "name": "Montgomery County",
    "osm_type": "relation",
    "osm_id": 2528724,
    "admin_level": "6",
    "level_name": "Counties/County-equivalents",
    "wikidata": "Q506697",
    "fips": null,
    "alt_name": null,
    "short_name": null,
    "official_name": null
  },
  {
    "country": "US",
    "state_abbr": "NC",
    "state_name": "North Carolina",
    "name": "Moore County",
    "osm_type": "relation",
    "osm_id": 2528725,
    "admin_level": "6",
    "level_name": "Counties/County-equivalents",
    "wikidata": "Q507782",
    "fips": null,
    "alt_name": null,
    "short_name": null,
    "official_name": null
  },
  {
    "country": "US",
    "state_abbr": "NC",
    "state_name": "North Carolina",
    "name": "Nash County",
    "osm_type": "relation",
    "osm_id": 2528726,
    "admin_level": "6",
    "level_name": "Counties/County-equivalents",
    "wikidata": "Q506235",
    "fips": null,
    "alt_name": null,
    "short_name": null,
    "official_name": null
  },
  {
    "country": "US",
    "state_abbr": "NC",
    "state_name": "North Carolina",
    "name": "New Hanover County",
    "osm_type": "relation",
    "osm_id": 2528727,
    "admin_level": "6",
    "level_name": "Counties/County-equivalents",
    "wikidata": "Q508209",
    "fips": null,
    "alt_name": null,
    "short_name": null,
    "official_name": null
  },
  {
    "country": "US",
    "state_abbr": "NC",
    "state_name": "North Carolina",
    "name": "Northampton County",
    "osm_type": "relation",
    "osm_id": 2528728,
    "admin_level": "6",
    "level_name": "Counties/County-equivalents",
    "wikidata": "Q506676",
    "fips": null,
    "alt_name": null,
    "short_name": null,
    "official_name": null
  },
  {
    "country": "US",
    "state_abbr": "NC",
    "state_name": "North Carolina",
    "name": "Onslow County",
    "osm_type": "relation",
    "osm_id": 2528729,
    "admin_level": "6",
    "level_name": "Counties/County-equivalents",
    "wikidata": "Q508220",
    "fips": null,
    "alt_name": null,
    "short_name": null,
    "official_name": null
  },
  {
    "country": "US",
    "state_abbr": "NC",
    "state_name": "North Carolina",
    "name": "Orange County",
    "osm_type": "relation",
    "osm_id": 2528730,
    "admin_level": "6",
    "level_name": "Counties/County-equivalents",
    "wikidata": "Q507957",
    "fips": null,
    "alt_name": null,
    "short_name": null,
    "official_name": null
  },
  {
    "country": "US",
    "state_abbr": "NC",
    "state_name": "North Carolina",
    "name": "Pamlico County",
    "osm_type": "relation",
    "osm_id": 2528731,
    "admin_level": "6",
    "level_name": "Counties/County-equivalents",
    "wikidata": "Q507616",
    "fips": null,
    "alt_name": null,
    "short_name": null,
    "official_name": null
  },
  {
    "country": "US",
    "state_abbr": "NC",
    "state_name": "North Carolina",
    "name": "Pender County",
    "osm_type": "relation",
    "osm_id": 2528732,
    "admin_level": "6",
    "level_name": "Counties/County-equivalents",
    "wikidata": "Q507826",
    "fips": null,
    "alt_name": null,
    "short_name": null,
    "official_name": null
  },
  {
    "country": "US",
    "state_abbr": "NC",
    "state_name": "North Carolina",
    "name": "Person County",
    "osm_type": "relation",
    "osm_id": 2528733,
    "admin_level": "6",
    "level_name": "Counties/County-equivalents",
    "wikidata": "Q508271",
    "fips": null,
    "alt_name": null,
    "short_name": null,
    "official_name": null
  },
  {
    "country": "US",
    "state_abbr": "NC",
    "state_name": "North Carolina",
    "name": "Pitt County",
    "osm_type": "relation",
    "osm_id": 2528734,
    "admin_level": "6",
    "level_name": "Counties/County-equivalents",
    "wikidata": "Q506220",
    "fips": null,
    "alt_name": null,
    "short_name": null,
    "official_name": null
  },
  {
    "country": "US",
    "state_abbr": "NC",
    "state_name": "North Carolina",
    "name": "Polk County",
    "osm_type": "relation",
    "osm_id": 2528735,
    "admin_level": "6",
    "level_name": "Counties/County-equivalents",
    "wikidata": "Q507892",
    "fips": null,
    "alt_name": null,
    "short_name": null,
    "official_name": null
  },
  {
    "country": "US",
    "state_abbr": "NC",
    "state_name": "North Carolina",
    "name": "Randolph County",
    "osm_type": "relation",
    "osm_id": 2528736,
    "admin_level": "6",
    "level_name": "Counties/County-equivalents",
    "wikidata": "Q507943",
    "fips": null,
    "alt_name": null,
    "short_name": null,
    "official_name": null
  },
  {
    "country": "US",
    "state_abbr": "NC",
    "state_name": "North Carolina",
    "name": "Richmond County",
    "osm_type": "relation",
    "osm_id": 2528737,
    "admin_level": "6",
    "level_name": "Counties/County-equivalents",
    "wikidata": "Q507870",
    "fips": null,
    "alt_name": null,
    "short_name": null,
    "official_name": null
  },
  {
    "country": "US",
    "state_abbr": "NC",
    "state_name": "North Carolina",
    "name": "Robeson County",
    "osm_type": "relation",
    "osm_id": 2528738,
    "admin_level": "6",
    "level_name": "Counties/County-equivalents",
    "wikidata": "Q507733",
    "fips": null,
    "alt_name": null,
    "short_name": null,
    "official_name": null
  },
  {
    "country": "US",
    "state_abbr": "NC",
    "state_name": "North Carolina",
    "name": "Rockingham County",
    "osm_type": "relation",
    "osm_id": 2528739,
    "admin_level": "6",
    "level_name": "Counties/County-equivalents",
    "wikidata": "Q505422",
    "fips": null,
    "alt_name": null,
    "short_name": null,
    "official_name": null
  },
  {
    "country": "US",
    "state_abbr": "NC",
    "state_name": "North Carolina",
    "name": "Rowan County",
    "osm_type": "relation",
    "osm_id": 2528740,
    "admin_level": "6",
    "level_name": "Counties/County-equivalents",
    "wikidata": "Q507966",
    "fips": null,
    "alt_name": null,
    "short_name": null,
    "official_name": null
  },
  {
    "country": "US",
    "state_abbr": "NC",
    "state_name": "North Carolina",
    "name": "Rutherford County",
    "osm_type": "relation",
    "osm_id": 2528741,
    "admin_level": "6",
    "level_name": "Counties/County-equivalents",
    "wikidata": "Q508254",
    "fips": null,
    "alt_name": null,
    "short_name": null,
    "official_name": null
  },
  {
    "country": "US",
    "state_abbr": "NC",
    "state_name": "North Carolina",
    "name": "Sampson County",
    "osm_type": "relation",
    "osm_id": 2528742,
    "admin_level": "6",
    "level_name": "Counties/County-equivalents",
    "wikidata": "Q507722",
    "fips": null,
    "alt_name": null,
    "short_name": null,
    "official_name": null
  },
  {
    "country": "US",
    "state_abbr": "NC",
    "state_name": "North Carolina",
    "name": "Scotland County",
    "osm_type": "relation",
    "osm_id": 2528743,
    "admin_level": "6",
    "level_name": "Counties/County-equivalents",
    "wikidata": "Q506690",
    "fips": null,
    "alt_name": null,
    "short_name": null,
    "official_name": null
  },
  {
    "country": "US",
    "state_abbr": "NC",
    "state_name": "North Carolina",
    "name": "Stanly County",
    "osm_type": "relation",
    "osm_id": 2528744,
    "admin_level": "6",
    "level_name": "Counties/County-equivalents",
    "wikidata": "Q507798",
    "fips": null,
    "alt_name": null,
    "short_name": null,
    "official_name": null
  },
  {
    "country": "US",
    "state_abbr": "NC",
    "state_name": "North Carolina",
    "name": "Stokes County",
    "osm_type": "relation",
    "osm_id": 2528745,
    "admin_level": "6",
    "level_name": "Counties/County-equivalents",
    "wikidata": "Q506682",
    "fips": null,
    "alt_name": null,
    "short_name": null,
    "official_name": null
  },
  {
    "country": "US",
    "state_abbr": "NC",
    "state_name": "North Carolina",
    "name": "Surry County",
    "osm_type": "relation",
    "osm_id": 2528746,
    "admin_level": "6",
    "level_name": "Counties/County-equivalents",
    "wikidata": "Q507881",
    "fips": null,
    "alt_name": null,
    "short_name": null,
    "official_name": null
  },
  {
    "country": "US",
    "state_abbr": "NC",
    "state_name": "North Carolina",
    "name": "Swain County",
    "osm_type": "relation",
    "osm_id": 2528747,
    "admin_level": "6",
    "level_name": "Counties/County-equivalents",
    "wikidata": "Q496197",
    "fips": null,
    "alt_name": null,
    "short_name": null,
    "official_name": null
  },
  {
    "country": "US",
    "state_abbr": "NC",
    "state_name": "North Carolina",
    "name": "Transylvania County",
    "osm_type": "relation",
    "osm_id": 2528748,
    "admin_level": "6",
    "level_name": "Counties/County-equivalents",
    "wikidata": "Q507743",
    "fips": null,
    "alt_name": null,
    "short_name": null,
    "official_name": null
  },
  {
    "country": "US",
    "state_abbr": "NC",
    "state_name": "North Carolina",
    "name": "Tyrrell County",
    "osm_type": "relation",
    "osm_id": 2528749,
    "admin_level": "6",
    "level_name": "Counties/County-equivalents",
    "wikidata": "Q507918",
    "fips": null,
    "alt_name": null,
    "short_name": null,
    "official_name": null
  },
  {
    "country": "US",
    "state_abbr": "NC",
    "state_name": "North Carolina",
    "name": "Union County",
    "osm_type": "relation",
    "osm_id": 2528750,
    "admin_level": "6",
    "level_name": "Counties/County-equivalents",
    "wikidata": "Q508247",
    "fips": null,
    "alt_name": null,
    "short_name": null,
    "official_name": null
  },
  {
    "country": "US",
    "state_abbr": "NC",
    "state_name": "North Carolina",
    "name": "Vance County",
    "osm_type": "relation",
    "osm_id": 2528751,
    "admin_level": "6",
    "level_name": "Counties/County-equivalents",
    "wikidata": "Q507981",
    "fips": null,
    "alt_name": null,
    "short_name": null,
    "official_name": null
  },
  {
    "country": "US",
    "state_abbr": "NC",
    "state_name": "North Carolina",
    "name": "Warren County",
    "osm_type": "relation",
    "osm_id": 2528752,
    "admin_level": "6",
    "level_name": "Counties/County-equivalents",
    "wikidata": "Q507853",
    "fips": null,
    "alt_name": null,
    "short_name": null,
    "official_name": null
  },
  {
    "country": "US",
    "state_abbr": "NC",
    "state_name": "North Carolina",
    "name": "Washington County",
    "osm_type": "relation",
    "osm_id": 2528753,
    "admin_level": "6",
    "level_name": "Counties/County-equivalents",
    "wikidata": "Q507587",
    "fips": null,
    "alt_name": null,
    "short_name": null,
    "official_name": null
  },
  {
    "country": "US",
    "state_abbr": "NC",
    "state_name": "North Carolina",
    "name": "Watauga County",
    "osm_type": "relation",
    "osm_id": 2528754,
    "admin_level": "6",
    "level_name": "Counties/County-equivalents",
    "wikidata": "Q502880",
    "fips": null,
    "alt_name": null,
    "short_name": null,
    "official_name": null
  },
  {
    "country": "US",
    "state_abbr": "NC",
    "state_name": "North Carolina",
    "name": "Wayne County",
    "osm_type": "relation",
    "osm_id": 2528755,
    "admin_level": "6",
    "level_name": "Counties/County-equivalents",
    "wikidata": "Q506569",
    "fips": null,
    "alt_name": null,
    "short_name": null,
    "official_name": null
  },
  {
    "country": "US",
    "state_abbr": "NC",
    "state_name": "North Carolina",
    "name": "Wilkes County",
    "osm_type": "relation",
    "osm_id": 2528756,
    "admin_level": "6",
    "level_name": "Counties/County-equivalents",
    "wikidata": "Q430328",
    "fips": null,
    "alt_name": null,
    "short_name": null,
    "official_name": null
  },
  {
    "country": "US",
    "state_abbr": "NC",
    "state_name": "North Carolina",
    "name": "Wilson County",
    "osm_type": "relation",
    "osm_id": 2528757,
    "admin_level": "6",
    "level_name": "Counties/County-equivalents",
    "wikidata": "Q510900",
    "fips": null,
    "alt_name": null,
    "short_name": null,
    "official_name": null
  },
  {
    "country": "US",
    "state_abbr": "NC",
    "state_name": "North Carolina",
    "name": "Yadkin County",
    "osm_type": "relation",
    "osm_id": 2528758,
    "admin_level": "6",
    "level_name": "Counties/County-equivalents",
    "wikidata": "Q497284",
    "fips": null,
    "alt_name": null,
    "short_name": null,
    "official_name": null
  },
  {
    "country": "US",
    "state_abbr": "NC",
    "state_name": "North Carolina",
    "name": "Yancey County",
    "osm_type": "relation",
    "osm_id": 2528759,
    "admin_level": "6",
    "level_name": "Counties/County-equivalents",
    "wikidata": "Q502487",
    "fips": null,
    "alt_name": null,
    "short_name": null,
    "official_name": null
  }
]