[
  {
    "country": "US",
    "state_abbr": "MN",
    "state_name": "Minnesota",
    "name": "Arnold",
    "osm_type": "relation",
    "osm_id": 136662,
    "admin_level": "9",
    "level_name": "Wards/Districts",
    "wikidata": "Q1926579",
    "fips": null,
    "alt_name": null,
    "short_name": null,
    "official_name": null
  },
  {
    "country": "US",
    "state_abbr": "MN",
    "state_name": "Minnesota",
    "name": "Hamline - Midway",
    "osm_type": "relation",
    "osm_id": 5258303,
    "admin_level": "9",
    "level_name": "Wards/Districts",
    "wikidata": null,
    "fips": null,
    "alt_name": null,
    "short_name": null,
    "official_name": null
  },
  {
    "country": "US",
    "state_abbr": "MN",
    "state_name": "Minnesota",
    "name": "Southeast",
    "osm_type": "relation",
    "osm_id": 13238003,
    "admin_level": "9",
    "level_name": "Wards/Districts",
    "wikidata": null,
    "fips": null,
    "alt_name": null,
    "short_name": null,
    "official_name": null
  },
  {
    "country": "US",
    "state_abbr": "MN",
    "state_name": "Minnesota",
    "name": "Dayton's Bluff",
    "osm_type": "relation",
    "osm_id": 13238225,
    "admin_level": "9",
    "level_name": "Wards/Districts",
    "wikidata": "Q5243468",
    "fips": null,
    "alt_name": null,
    "short_name": null,
    "official_name": null
  },
  {
    "country": "US",
    "state_abbr": "MN",
    "state_name": "Minnesota",
    "name": "West Side",
    "osm_type": "relation",
    "osm_id": 13238309,
    "admin_level": "9",
    "level_name": "Wards/Districts",
    "wikidata": null,
    "fips": null,
    "alt_name": null,
    "short_name": null,
    "official_name": null
  },
  {
    "country": "US",
    "state_abbr": "MN",
    "state_name": "Minnesota",
    "name": "Greater East Side",
    "osm_type": "relation",
    "osm_id": 13238325,
    "admin_level": "9",
    "level_name": "Wards/Districts",
    "wikidata": null,
    "fips": null,
    "alt_name": null,
    "short_name": null,
    "official_name": null
  },
  {
    "country": "US",
    "state_abbr": "MN",
    "state_name": "Minnesota",
    "name": "Payne - Phalen",
    "osm_type": "relation",
    "osm_id": 13238349,
    "admin_level": "9",
    "level_name": "Wards/Districts",
    "wikidata": null,
    "fips": null,
    "alt_name": null,
    "short_name": null,
    "official_name": null
  },
  {
    "country": "US",
    "state_abbr": "MN",
    "state_name": "Minnesota",
    "name": "North End",
    "osm_type": "relation",
    "osm_id": 13238531,
    "admin_level": "9",
    "level_name": "Wards/Districts",
    "wikidata": "Q96396323",
    "fips": null,
    "alt_name": null,
    "short_name": null,
    "official_name": null
  },
  {
    "country": "US",
    "state_abbr": "MN",
    "state_name": "Minnesota",
    "name": "Downtown",
    "osm_type": "relation",
    "osm_id": 13238593,
    "admin_level": "9",
    "level_name": "Wards/Districts",
    "wikidata": "Q30066020",
    "fips": null,
    "alt_name": null,
    "short_name": null,
    "official_name": null
  },
  {
    "country": "US",
    "state_abbr": "MN",
    "state_name": "Minnesota",
    "name": "West Seventh - Fort Road",
    "osm_type": "relation",
    "osm_id": 13241062,
    "admin_level": "9",
    "level_name": "Wards/Districts",
    "wikidata": "Q7986469",
    "fips": null,
    "alt_name": null,
    "short_name": null,
    "official_name": null
  },
  {
    "country": "US",
    "state_abbr": "MN",
    "state_name": "Minnesota",
    "name": "Highland",
    "osm_type": "relation",
    "osm_id": 13241164,
    "admin_level": "9",
    "level_name": "Wards/Districts",
    "wikidata": "Q5758942",
    "fips": null,
    "alt_name": null,
    "short_name": null,
    "official_name": null
  },
  {
    "country": "US",
    "state_abbr": "MN",
    "state_name": "Minnesota",
    "name": "Summit Hill",
    "osm_type": "relation",
    "osm_id": 13244174,
    "admin_level": "9",
    "level_name": "Wards/Districts",
    "wikidata": null,
    "fips": null,
    "alt_name": null,
    "short_name": null,
    "official_name": null
  },
  {
    "country": "US",
    "state_abbr": "MN",
    "state_name": "Minnesota",
    "name": "Macalester - Groveland",
    "osm_type": "relation",
    "osm_id": 13244175,
    "admin_level": "9",
    "level_name": "Wards/Districts",
    "wikidata": null,
    "fips": null,
    "alt_name": null,
    "short_name": null,
    "official_name": null
  },
  {
    "country": "US",
    "state_abbr": "MN",
    "state_name": "Minnesota",
    "name": "Summit - University",
    "osm_type": "relation",
    "osm_id": 13244309,
    "admin_level": "9",
    "level_name": "Wards/Districts",
    "wikidata": null,
    "fips": null,
    "alt_name": null,
    "short_name": null,
    "official_name": null
  },
  {
    "country": "US",
    "state_abbr": "MN",
    "state_name": "Minnesota",
    "name": "Union Park",
    "osm_type": "relation",
    "osm_id": 13244310,
    "admin_level": "9",
    "level_name": "Wards/Districts",
    "wikidata": "Q17066619",
    "fips": null,
    "alt_name": null,
    "short_name": null,
    "official_name": null
  },
  {
    "country": "US",
    "state_abbr": "MN",
    "state_name": "Minnesota",
    "name": "Saint Anthony Park",
    "osm_type": "relation",
    "osm_id": 13248006,
    "admin_level": "9",
    "level_name": "Wards/Districts",
    "wikidata": "Q7400984",
    "fips": null,
    "alt_name": null,
    "short_name": null,
    "official_name": null
  },
  {
    "country": "US",
    "state_abbr": "MN",
    "state_name": "Minnesota",
    "name": "Como Park",
    "osm_type": "relation",
    "osm_id": 13248264,
    "admin_level": "9",
    "level_name": "Wards/Districts",
    "wikidata": "Q56796227",
    "fips": null,
    "alt_name": null,
    "short_name": null,
    "official_name": null
  },
  {
    "country": "US",
    "state_abbr": "MN",
    "state_name": "Minnesota",
    "name": "Frogtown",
    "osm_type": "relation",
    "osm_id": 13248265,
    "admin_level": "9",
    "level_name": "Wards/Districts",
    "wikidata": "Q5505308",
    "fips": null,
    "alt_name": null,
    "short_name": null,
    "official_name": null
  },
  {
    "country": "US",
    "state_abbr": "MN",
    "state_name": "Minnesota",
    "name": "Southwest",
    "osm_type": "relation",
    "osm_id": 13275977,
    "admin_level": "9",
    "level_name": "Wards/Districts",
    "wikidata": "Q2351324",
    "fips": null,
    "alt_name": null,
    "short_name": null,
    "official_name": null
  },
  {
    "country": "US",
    "state_abbr": "MN",
    "state_name": "Minnesota",
    "name": "Calhoun Isles",
    "osm_type": "relation",
    "osm_id": 13276014,
    "admin_level": "9",
    "level_name": "Wards/Districts",
    "wikidata": "Q5019782",
    "fips": null,
    "alt_name": null,
    "short_name": null,
    "official_name": null
  },
  {
    "country": "US",
    "state_abbr": "MN",
    "state_name": "Minnesota",
    "name": "Fond du Lac",
    "osm_type": "relation",
    "osm_id": 15792176,
    "admin_level": "9",
    "level_name": "Wards/Districts",
    "wikidata": "Q5464961",
    "fips": null,
    "alt_name": null,
    "short_name": null,
    "official_name": null
  },
  {
    "country": "US",
    "state_abbr": "MN",
    "state_name": "Minnesota",
    "name": "Midway Annex",
    "osm_type": "relation",
    "osm_id": 15792177,
    "admin_level": "9",
    "level_name": "Wards/Districts",
    "wikidata": null,
    "fips": null,
    "alt_name": null,
    "short_name": null,
    "official_name": null
  },
  {
    "country": "US",
    "state_abbr": "MN",
    "state_name": "Minnesota",
    "name": "Smithville",
    "osm_type": "relation",
    "osm_id": 15792178,
    "admin_level": "9",
    "level_name": "Wards/Districts",
    "wikidata": "Q14693049",
    "fips": null,
    "alt_name": null,
    "short_name": null,
    "official_name": null
  },
  {
    "country": "US",
    "state_abbr": "MN",
    "state_name": "Minnesota",
    "name": "Gary-New Duluth",
    "osm_type": "relation",
    "osm_id": 15792180,
    "admin_level": "9",
    "level_name": "Wards/Districts",
    "wikidata": "Q5526228",
    "fips": null,
    "alt_name": null,
    "short_name": null,
    "official_name": null
  },
  {
    "country": "US",
    "state_abbr": "MN",
    "state_name": "Minnesota",
    "name": "Morgan Park",
    "osm_type": "relation",
    "osm_id": 15792181,
    "admin_level": "9",
    "level_name": "Wards/Districts",
    "wikidata": "Q6911801",
    "fips": null,
    "alt_name": null,
    "short_name": null,
    "official_name": null
  },
  {
    "country": "US",
    "state_abbr": "MN",
    "state_name": "Minnesota",
    "name": "Riverside",
    "osm_type": "relation",
    "osm_id": 15792298,
    "admin_level": "9",
    "level_name": "Wards/Districts",
    "wikidata": "Q7338407",
    "fips": null,
    "alt_name": null,
    "short_name": null,
    "official_name": null
  },
  {
    "country": "US",
    "state_abbr": "MN",
    "state_name": "Minnesota",
    "name": "Norton Park",
    "osm_type": "relation",
    "osm_id": 15792337,
    "admin_level": "9",
    "level_name": "Wards/Districts",
    "wikidata": "Q7060670",
    "fips": null,
    "alt_name": null,
    "short_name": null,
    "official_name": null
  },
  {
    "country": "US",
    "state_abbr": "MN",
    "state_name": "Minnesota",
    "name": "Bayview Heights",
    "osm_type": "relation",
    "osm_id": 15792563,
    "admin_level": "9",
    "level_name": "Wards/Districts",
    "wikidata": "Q4875011",
    "fips": null,
    "alt_name": null,
    "short_name": null,
    "official_name": null
  },
  {
    "country": "US",
    "state_abbr": "MN",
    "state_name": "Minnesota",
    "name": "Cody",
    "osm_type": "relation",
    "osm_id": 15792581,
    "admin_level": "9",
    "level_name": "Wards/Districts",
    "wikidata": "Q5140394",
    "fips": null,
    "alt_name": null,
    "short_name": null,
    "official_name": null
  },
  {
    "country": "US",
    "state_abbr": "MN",
    "state_name": "Minnesota",
    "name": "Piedmont Heights",
    "osm_type": "relation",
    "osm_id": 15792598,
    "admin_level": "9",
    "level_name": "Wards/Districts",
    "wikidata": "Q7191513",
    "fips": null,
    "alt_name": null,
    "short_name": null,
    "official_name": null
  },
  {
    "country": "US",
    "state_abbr": "MN",
    "state_name": "Minnesota",
    "name": "Fairmount",
    "osm_type": "relation",
    "osm_id": 15792652,
    "admin_level": "9",
    "level_name": "Wards/Districts",
    "wikidata": "Q5430623",
    "fips": null,
    "alt_name": null,
    "short_name": null,
    "official_name": null
  },
  {
    "country": "US",
    "state_abbr": "MN",
    "state_name": "Minnesota",
    "name": "Irving",
    "osm_type": "relation",
    "osm_id": 15792668,
    "admin_level": "9",
    "level_name": "Wards/Districts",
    "wikidata": "Q6074444",
    "fips": null,
    "alt_name": null,
    "short_name": null,
    "official_name": null
  },
  {
    "country": "US",
    "state_abbr": "MN",
    "state_name": "Minnesota",
    "name": "Oneota",
    "osm_type": "relation",
    "osm_id": 15792676,
    "admin_level": "9",
    "level_name": "Wards/Districts",
    "wikidata": "Q7093727",
    "fips": null,
    "alt_name": null,
    "short_name": null,
    "official_name": null
  },
  {
    "country": "US",
    "state_abbr": "MN",
    "state_name": "Minnesota",
    "name": "Spirit Valley",
    "osm_type": "relation",
    "osm_id": 15792680,
    "admin_level": "9",
    "level_name": "Wards/Districts",
    "wikidata": "Q7577919",
    "fips": null,
    "alt_name": null,
    "short_name": null,
    "official_name": null
  },
  {
    "country": "US",
    "state_abbr": "MN",
    "state_name": "Minnesota",
    "name": "Lincoln Park",
    "osm_type": "relation",
    "osm_id": 15792714,
    "admin_level": "9",
    "level_name": "Wards/Districts",
    "wikidata": "Q6550916",
    "fips": null,
    "alt_name": null,
    "short_name": null,
    "official_name": null
  },
  {
    "country": "US",
    "state_abbr": "MN",
    "state_name": "Minnesota",
    "name": "Park Point",
    "osm_type": "relation",
    "osm_id": 15792724,
    "admin_level": "9",
    "level_name": "Wards/Districts",
    "wikidata": "Q1937369",
    "fips": null,
    "alt_name": null,
    "short_name": null,
    "official_name": null
  },
  {
    "country": "US",
    "state_abbr": "MN",
    "state_name": "Minnesota",
    "name": "Duluth Heights",
    "osm_type": "relation",
    "osm_id": 15792760,
    "admin_level": "9",
    "level_name": "Wards/Districts",
    "wikidata": "Q5313512",
    "fips": null,
    "alt_name": null,
    "short_name": null,
    "official_name": null
  },
  {
    "country": "US",
    "state_abbr": "MN",
    "state_name": "Minnesota",
    "name": "North Shore",
    "osm_type": "relation",
    "osm_id": 15792816,
    "admin_level": "9",
    "level_name": "Wards/Districts",
    "wikidata": "Q7056652",
    "fips": null,
    "alt_name": null,
    "short_name": null,
    "official_name": null
  },
  {
    "country": "US",
    "state_abbr": "MN",
    "state_name": "Minnesota",
    "name": "Lakeside-Lester Park",
    "osm_type": "relation",
    "osm_id": 15792829,
    "admin_level": "9",
    "level_name": "Wards/Districts",
    "wikidata": "Q14692760",
    "fips": null,
    "alt_name": null,
    "short_name": null,
    "official_name": null
  },
  {
    "country": "US",
    "state_abbr": "MN",
    "state_name": "Minnesota",
    "name": "Rice Lake Annex",
    "osm_type": "relation",
    "osm_id": 15792844,
    "admin_level": "9",
    "level_name": "Wards/Districts",
    "wikidata": null,
    "fips": null,
    "alt_name": null,
    "short_name": null,
    "official_name": null
  },
  {
    "country": "US",
    "state_abbr": "MN",
    "state_name": "Minnesota",
    "name": "Central Hillside",
    "osm_type": "relation",
    "osm_id": 15937631,
    "admin_level": "9",
    "level_name": "Wards/Districts",
    "wikidata": null,
    "fips": null,
    "alt_name": null,
    "short_name": null,
    "official_name": null
  },
  {
    "country": "US",
    "state_abbr": "MN",
    "state_name": "Minnesota",
    "name": "Central Business District",
    "osm_type": "relation",
    "osm_id": 15937632,
    "admin_level": "9",
    "level_name": "Wards/Districts",
    "wikidata": null,
    "fips": null,
    "alt_name": null,
    "short_name": null,
    "official_name": null
  },
  {
    "country": "US",
    "state_abbr": "MN",
    "state_name": "Minnesota",
    "name": "East Hillside",
    "osm_type": "relation",
    "osm_id": 15937633,
    "admin_level": "9",
    "level_name": "Wards/Districts",
    "wikidata": null,
    "fips": null,
    "alt_name": null,
    "short_name": null,
    "official_name": null
  }
]