[
  {
    "country": "CA",
    "state_abbr": "NB",
    "state_name": "New Brunswick",
    "name": "Duck Islands",
    "osm_type": "way",
    "osm_id": 117019403,
    "admin_level": "9",
    "level_name": "Wards/Districts",
    "wikidata": null,
    "fips": null,
    "alt_name": null,
    "short_name": null,
    "official_name": null
  },
  {
    "country": "CA",
    "state_abbr": "NB",
    "state_name": "New Brunswick",
    "name": "Nantucket Island",
    "osm_type": "way",
    "osm_id": 117151083,
    "admin_level": "9",
    "level_name": "Wards/Districts",
    "wikidata": null,
    "fips": null,
    "alt_name": null,
    "short_name": null,
    "official_name": null
  },
  {
    "country": "CA",
    "state_abbr": "NB",
    "state_name": "New Brunswick",
    "name": "Low Duck Island",
    "osm_type": "way",
    "osm_id": 117151457,
    "admin_level": "9",
    "level_name": "Wards/Districts",
    "wikidata": null,
    "fips": null,
    "alt_name": null,
    "short_name": null,
    "official_name": null
  },
  {
    "country": "CA",
    "state_abbr": "NB",
    "state_name": "New Brunswick",
    "name": "Great Duck Island",
    "osm_type": "way",
    "osm_id": 117151482,
    "admin_level": "9",
    "level_name": "Wards/Districts",
    "wikidata": null,
    "fips": null,
    "alt_name": null,
    "short_name": null,
    "official_name": null
  },
  {
    "country": "CA",
    "state_abbr": "NB",
    "state_name": "New Brunswick",
    "name": "Long Island",
    "osm_type": "way",
    "osm_id": 117151615,
    "admin_level": "9",
    "level_name": "Wards/Districts",
    "wikidata": null,
    "fips": null,
    "alt_name": null,
    "short_name": null,
    "official_name": null
  },
  {
    "country": "CA",
    "state_abbr": "NB",
    "state_name": "New Brunswick",
    "name": "Dinner Island",
    "osm_type": "way",
    "osm_id": 369599588,
    "admin_level": "9",
    "level_name": "Wards/Districts",
    "wikidata": null,
    "fips": null,
    "alt_name": null,
    "short_name": null,
    "official_name": null
  },
  {
    "country": "CA",
    "state_abbr": "NB",
    "state_name": "New Brunswick",
    "name": "Nub Island",
    "osm_type": "way",
    "osm_id": 369611346,
    "admin_level": "9",
    "level_name": "Wards/Districts",
    "wikidata": null,
    "fips": null,
    "alt_name": null,
    "short_name": null,
    "official_name": null
  },
  {
    "country": "CA",
    "state_abbr": "NB",
    "state_name": "New Brunswick",
    "name": "Pumpkin Islet",
    "osm_type": "way",
    "osm_id": 696022265,
    "admin_level": "9",
    "level_name": "Wards/Districts",
    "wikidata": null,
    "fips": null,
    "alt_name": null,
    "short_name": null,
    "official_name": null
  },
  {
    "country": "CA",
    "state_abbr": "NB",
    "state_name": "New Brunswick",
    "name": "West Pumpkin Island",
    "osm_type": "way",
    "osm_id": 696022271,
    "admin_level": "9",
    "level_name": "Wards/Districts",
    "wikidata": null,
    "fips": null,
    "alt_name": null,
    "short_name": null,
    "official_name": null
  },
  {
    "country": "CA",
    "state_abbr": "NB",
    "state_name": "New Brunswick",
    "name": "Cull Island",
    "osm_type": "way",
    "osm_id": 696022336,
    "admin_level": "9",
    "level_name": "Wards/Districts",
    "wikidata": null,
    "fips": null,
    "alt_name": null,
    "short_name": null,
    "official_name": null
  },
  {
    "country": "CA",
    "state_abbr": "NB",
    "state_name": "New Brunswick",
    "name": "Western Green Island",
    "osm_type": "way",
    "osm_id": 696022337,
    "admin_level": "9",
    "level_name": "Wards/Districts",
    "wikidata": "Q22599267",
    "fips": null,
    "alt_name": null,
    "short_name": null,
    "official_name": null
  },
  {
    "country": "CA",
    "state_abbr": "NB",
    "state_name": "New Brunswick",
    "name": "South Green Island",
    "osm_type": "way",
    "osm_id": 696022339,
    "admin_level": "9",
    "level_name": "Wards/Districts",
    "wikidata": null,
    "fips": null,
    "alt_name": null,
    "short_name": null,
    "official_name": null
  },
  {
    "country": "CA",
    "state_abbr": "NB",
    "state_name": "New Brunswick",
    "name": "North Green Island",
    "osm_type": "way",
    "osm_id": 696022340,
    "admin_level": "9",
    "level_name": "Wards/Districts",
    "wikidata": null,
    "fips": null,
    "alt_name": null,
    "short_name": null,
    "official_name": null
  },
  {
    "country": "CA",
    "state_abbr": "NB",
    "state_name": "New Brunswick",
    "name": "High Duck Island",
    "osm_type": "way",
    "osm_id": 696022341,
    "admin_level": "9",
    "level_name": "Wards/Districts",
    "wikidata": null,
    "fips": null,
    "alt_name": null,
    "short_name": null,
    "official_name": null
  },
  {
    "country": "CA",
    "state_abbr": "NB",
    "state_name": "New Brunswick",
    "name": "Sheep Island",
    "osm_type": "way",
    "osm_id": 696022343,
    "admin_level": "9",
    "level_name": "Wards/Districts",
    "wikidata": null,
    "fips": null,
    "alt_name": null,
    "short_name": null,
    "official_name": null
  },
  {
    "country": "CA",
    "state_abbr": "NB",
    "state_name": "New Brunswick",
    "name": "Hay Island",
    "osm_type": "way",
    "osm_id": 696022344,
    "admin_level": "9",
    "level_name": "Wards/Districts",
    "wikidata": null,
    "fips": null,
    "alt_name": null,
    "short_name": null,
    "official_name": null
  },
  {
    "country": "CA",
    "state_abbr": "NB",
    "state_name": "New Brunswick",
    "name": "Wood Island",
    "osm_type": "way",
    "osm_id": 696022348,
    "admin_level": "9",
    "level_name": "Wards/Districts",
    "wikidata": null,
    "fips": null,
    "alt_name": null,
    "short_name": null,
    "official_name": null
  },
  {
    "country": "CA",
    "state_abbr": "NB",
    "state_name": "New Brunswick",
    "name": "Kent Island",
    "osm_type": "way",
    "osm_id": 696022349,
    "admin_level": "9",
    "level_name": "Wards/Districts",
    "wikidata": null,
    "fips": null,
    "alt_name": null,
    "short_name": null,
    "official_name": null
  },
  {
    "country": "CA",
    "state_abbr": "NB",
    "state_name": "New Brunswick",
    "name": "Ross Island",
    "osm_type": "way",
    "osm_id": 696022352,
    "admin_level": "9",
    "level_name": "Wards/Districts",
    "wikidata": null,
    "fips": null,
    "alt_name": null,
    "short_name": null,
    "official_name": null
  },
  {
    "country": "CA",
    "state_abbr": "NB",
    "state_name": "New Brunswick",
    "name": "West Isles Parish",
    "osm_type": "way",
    "osm_id": 696041828,
    "admin_level": "9",
    "level_name": "Wards/Districts",
    "wikidata": null,
    "fips": null,
    "alt_name": null,
    "short_name": null,
    "official_name": null
  },
  {
    "country": "CA",
    "state_abbr": "NB",
    "state_name": "New Brunswick",
    "name": "West Isles Parish",
    "osm_type": "way",
    "osm_id": 696041838,
    "admin_level": "9",
    "level_name": "Wards/Districts",
    "wikidata": null,
    "fips": null,
    "alt_name": null,
    "short_name": null,
    "official_name": null
  },
  {
    "country": "CA",
    "state_abbr": "NB",
    "state_name": "New Brunswick",
    "name": "West Isles Parish",
    "osm_type": "way",
    "osm_id": 696041839,
    "admin_level": "9",
    "level_name": "Wards/Districts",
    "wikidata": null,
    "fips": null,
    "alt_name": null,
    "short_name": null,
    "official_name": null
  },
  {
    "country": "CA",
    "state_abbr": "NB",
    "state_name": "New Brunswick",
    "name": "West Isles Parish",
    "osm_type": "way",
    "osm_id": 696041844,
    "admin_level": "9",
    "level_name": "Wards/Districts",
    "wikidata": null,
    "fips": null,
    "alt_name": null,
    "short_name": null,
    "official_name": null
  },
  {
    "country": "CA",
    "state_abbr": "NB",
    "state_name": "New Brunswick",
    "name": "The Nubble",
    "osm_type": "way",
    "osm_id": 696041846,
    "admin_level": "9",
    "level_name": "Wards/Districts",
    "wikidata": null,
    "fips": null,
    "alt_name": null,
    "short_name": null,
    "official_name": null
  },
  {
    "country": "CA",
    "state_abbr": "NB",
    "state_name": "New Brunswick",
    "name": "West Isles Parish",
    "osm_type": "way",
    "osm_id": 696041847,
    "admin_level": "9",
    "level_name": "Wards/Districts",
    "wikidata": null,
    "fips": null,
    "alt_name": null,
    "short_name": null,
    "official_name": null
  },
  {
    "country": "CA",
    "state_abbr": "NB",
    "state_name": "New Brunswick",
    "name": "West Isles Parish",
    "osm_type": "way",
    "osm_id": 696041849,
    "admin_level": "9",
    "level_name": "Wards/Districts",
    "wikidata": null,
    "fips": null,
    "alt_name": null,
    "short_name": null,
    "official_name": null
  },
  {
    "country": "CA",
    "state_abbr": "NB",
    "state_name": "New Brunswick",
    "name": "West Isles Parish",
    "osm_type": "way",
    "osm_id": 696041852,
    "admin_level": "9",
    "level_name": "Wards/Districts",
    "wikidata": null,
    "fips": null,
    "alt_name": null,
    "short_name": null,
    "official_name": null
  },
  {
    "country": "CA",
    "state_abbr": "NB",
    "state_name": "New Brunswick",
    "name": "The Pup",
    "osm_type": "way",
    "osm_id": 696041857,
    "admin_level": "9",
    "level_name": "Wards/Districts",
    "wikidata": null,
    "fips": null,
    "alt_name": null,
    "short_name": null,
    "official_name": null
  },
  {
    "country": "CA",
    "state_abbr": "NB",
    "state_name": "New Brunswick",
    "name": "Tinkers Island",
    "osm_type": "way",
    "osm_id": 696041860,
    "admin_level": "9",
    "level_name": "Wards/Districts",
    "wikidata": null,
    "fips": null,
    "alt_name": null,
    "short_name": null,
    "official_name": null
  },
  {
    "country": "CA",
    "state_abbr": "NB",
    "state_name": "New Brunswick",
    "name": "Little Mowat Island",
    "osm_type": "way",
    "osm_id": 696041861,
    "admin_level": "9",
    "level_name": "Wards/Districts",
    "wikidata": null,
    "fips": null,
    "alt_name": null,
    "short_name": null,
    "official_name": null
  },
  {
    "country": "CA",
    "state_abbr": "NB",
    "state_name": "New Brunswick",
    "name": "Crow Island",
    "osm_type": "way",
    "osm_id": 696041862,
    "admin_level": "9",
    "level_name": "Wards/Districts",
    "wikidata": null,
    "fips": null,
    "alt_name": null,
    "short_name": null,
    "official_name": null
  },
  {
    "country": "CA",
    "state_abbr": "NB",
    "state_name": "New Brunswick",
    "name": "Fish Island",
    "osm_type": "way",
    "osm_id": 696041867,
    "admin_level": "9",
    "level_name": "Wards/Districts",
    "wikidata": null,
    "fips": null,
    "alt_name": null,
    "short_name": null,
    "official_name": null
  },
  {
    "country": "CA",
    "state_abbr": "NB",
    "state_name": "New Brunswick",
    "name": "Popes Island",
    "osm_type": "way",
    "osm_id": 696041868,
    "admin_level": "9",
    "level_name": "Wards/Districts",
    "wikidata": null,
    "fips": null,
    "alt_name": null,
    "short_name": null,
    "official_name": null
  },
  {
    "country": "CA",
    "state_abbr": "NB",
    "state_name": "New Brunswick",
    "name": "West Isles Parish",
    "osm_type": "way",
    "osm_id": 696041869,
    "admin_level": "9",
    "level_name": "Wards/Districts",
    "wikidata": null,
    "fips": null,
    "alt_name": null,
    "short_name": null,
    "official_name": null
  },
  {
    "country": "CA",
    "state_abbr": "NB",
    "state_name": "New Brunswick",
    "name": "Sandy Island",
    "osm_type": "way",
    "osm_id": 696041872,
    "admin_level": "9",
    "level_name": "Wards/Districts",
    "wikidata": null,
    "fips": null,
    "alt_name": null,
    "short_name": null,
    "official_name": null
  },
  {
    "country": "CA",
    "state_abbr": "NB",
    "state_name": "New Brunswick",
    "name": "New Ireland",
    "osm_type": "way",
    "osm_id": 696041873,
    "admin_level": "9",
    "level_name": "Wards/Districts",
    "wikidata": null,
    "fips": null,
    "alt_name": null,
    "short_name": null,
    "official_name": null
  },
  {
    "country": "CA",
    "state_abbr": "NB",
    "state_name": "New Brunswick",
    "name": "Mowat Island",
    "osm_type": "way",
    "osm_id": 696041875,
    "admin_level": "9",
    "level_name": "Wards/Districts",
    "wikidata": null,
    "fips": null,
    "alt_name": null,
    "short_name": null,
    "official_name": null
  },
  {
    "country": "CA",
    "state_abbr": "NB",
    "state_name": "New Brunswick",
    "name": "Bar Island",
    "osm_type": "way",
    "osm_id": 696041876,
    "admin_level": "9",
    "level_name": "Wards/Districts",
    "wikidata": null,
    "fips": null,
    "alt_name": null,
    "short_name": null,
    "official_name": null
  },
  {
    "country": "CA",
    "state_abbr": "NB",
    "state_name": "New Brunswick",
    "name": "St. Helena Island",
    "osm_type": "way",
    "osm_id": 696041878,
    "admin_level": "9",
    "level_name": "Wards/Districts",
    "wikidata": null,
    "fips": null,
    "alt_name": null,
    "short_name": null,
    "official_name": null
  },
  {
    "country": "CA",
    "state_abbr": "NB",
    "state_name": "New Brunswick",
    "name": "Jameson Island",
    "osm_type": "way",
    "osm_id": 696041879,
    "admin_level": "9",
    "level_name": "Wards/Districts",
    "wikidata": null,
    "fips": null,
    "alt_name": null,
    "short_name": null,
    "official_name": null
  },
  {
    "country": "CA",
    "state_abbr": "NB",
    "state_name": "New Brunswick",
    "name": "Spurce Island",
    "osm_type": "way",
    "osm_id": 696041880,
    "admin_level": "9",
    "level_name": "Wards/Districts",
    "wikidata": null,
    "fips": null,
    "alt_name": null,
    "short_name": null,
    "official_name": null
  },
  {
    "country": "CA",
    "state_abbr": "NB",
    "state_name": "New Brunswick",
    "name": "Hardwood Island",
    "osm_type": "way",
    "osm_id": 696041881,
    "admin_level": "9",
    "level_name": "Wards/Districts",
    "wikidata": null,
    "fips": null,
    "alt_name": null,
    "short_name": null,
    "official_name": null
  },
  {
    "country": "CA",
    "state_abbr": "NB",
    "state_name": "New Brunswick",
    "name": "Barnes Island",
    "osm_type": "way",
    "osm_id": 696041882,
    "admin_level": "9",
    "level_name": "Wards/Districts",
    "wikidata": null,
    "fips": null,
    "alt_name": null,
    "short_name": null,
    "official_name": null
  },
  {
    "country": "CA",
    "state_abbr": "NB",
    "state_name": "New Brunswick",
    "name": "Adam Island",
    "osm_type": "way",
    "osm_id": 696041884,
    "admin_level": "9",
    "level_name": "Wards/Districts",
    "wikidata": null,
    "fips": null,
    "alt_name": null,
    "short_name": null,
    "official_name": null
  },
  {
    "country": "CA",
    "state_abbr": "NB",
    "state_name": "New Brunswick",
    "name": "Simpsons Island",
    "osm_type": "way",
    "osm_id": 696041885,
    "admin_level": "9",
    "level_name": "Wards/Districts",
    "wikidata": null,
    "fips": null,
    "alt_name": null,
    "short_name": null,
    "official_name": null
  },
  {
    "country": "CA",
    "state_abbr": "NB",
    "state_name": "New Brunswick",
    "name": "Parker Island",
    "osm_type": "way",
    "osm_id": 696041887,
    "admin_level": "9",
    "level_name": "Wards/Districts",
    "wikidata": null,
    "fips": null,
    "alt_name": null,
    "short_name": null,
    "official_name": null
  },
  {
    "country": "CA",
    "state_abbr": "NB",
    "state_name": "New Brunswick",
    "name": "Beans Island",
    "osm_type": "way",
    "osm_id": 696041888,
    "admin_level": "9",
    "level_name": "Wards/Districts",
    "wikidata": null,
    "fips": null,
    "alt_name": null,
    "short_name": null,
    "official_name": null
  },
  {
    "country": "CA",
    "state_abbr": "NB",
    "state_name": "New Brunswick",
    "name": "Macs Island",
    "osm_type": "way",
    "osm_id": 696041889,
    "admin_level": "9",
    "level_name": "Wards/Districts",
    "wikidata": null,
    "fips": null,
    "alt_name": null,
    "short_name": null,
    "official_name": null
  },
  {
    "country": "CA",
    "state_abbr": "NB",
    "state_name": "New Brunswick",
    "name": "Indian Island",
    "osm_type": "way",
    "osm_id": 696046557,
    "admin_level": "9",
    "level_name": "Wards/Districts",
    "wikidata": null,
    "fips": null,
    "alt_name": null,
    "short_name": null,
    "official_name": null
  },
  {
    "country": "CA",
    "state_abbr": "NB",
    "state_name": "New Brunswick",
    "name": "Bliss Island",
    "osm_type": "way",
    "osm_id": 696046558,
    "admin_level": "9",
    "level_name": "Wards/Districts",
    "wikidata": null,
    "fips": null,
    "alt_name": null,
    "short_name": null,
    "official_name": null
  },
  {
    "country": "CA",
    "state_abbr": "NB",
    "state_name": "New Brunswick",
    "name": "Navy Island",
    "osm_type": "way",
    "osm_id": 696507363,
    "admin_level": "9",
    "level_name": "Wards/Districts",
    "wikidata": null,
    "fips": null,
    "alt_name": null,
    "short_name": null,
    "official_name": null
  },
  {
    "country": "CA",
    "state_abbr": "NB",
    "state_name": "New Brunswick",
    "name": "Pocologon Island",
    "osm_type": "way",
    "osm_id": 696792984,
    "admin_level": "9",
    "level_name": "Wards/Districts",
    "wikidata": null,
    "fips": null,
    "alt_name": null,
    "short_name": null,
    "official_name": null
  },
  {
    "country": "CA",
    "state_abbr": "NB",
    "state_name": "New Brunswick",
    "name": "Flea island",
    "osm_type": "way",
    "osm_id": 696795564,
    "admin_level": "9",
    "level_name": "Wards/Districts",
    "wikidata": null,
    "fips": null,
    "alt_name": null,
    "short_name": null,
    "official_name": null
  },
  {
    "country": "CA",
    "state_abbr": "NB",
    "state_name": "New Brunswick",
    "name": "Hills Island",
    "osm_type": "way",
    "osm_id": 696795567,
    "admin_level": "9",
    "level_name": "Wards/Districts",
    "wikidata": null,
    "fips": null,
    "alt_name": null,
    "short_name": null,
    "official_name": null
  },
  {
    "country": "CA",
    "state_abbr": "NB",
    "state_name": "New Brunswick",
    "name": "White Horse Islet",
    "osm_type": "way",
    "osm_id": 696799819,
    "admin_level": "9",
    "level_name": "Wards/Districts",
    "wikidata": null,
    "fips": null,
    "alt_name": null,
    "short_name": null,
    "official_name": null
  },
  {
    "country": "CA",
    "state_abbr": "NB",
    "state_name": "New Brunswick",
    "name": "Cheney island",
    "osm_type": "way",
    "osm_id": 696799827,
    "admin_level": "9",
    "level_name": "Wards/Districts",
    "wikidata": null,
    "fips": null,
    "alt_name": null,
    "short_name": null,
    "official_name": null
  },
  {
    "country": "CA",
    "state_abbr": "NB",
    "state_name": "New Brunswick",
    "name": "Wood Island",
    "osm_type": "way",
    "osm_id": 696799828,
    "admin_level": "9",
    "level_name": "Wards/Districts",
    "wikidata": null,
    "fips": null,
    "alt_name": null,
    "short_name": null,
    "official_name": null
  },
  {
    "country": "CA",
    "state_abbr": "NB",
    "state_name": "New Brunswick",
    "name": "White Head Island",
    "osm_type": "way",
    "osm_id": 696799829,
    "admin_level": "9",
    "level_name": "Wards/Districts",
    "wikidata": null,
    "fips": null,
    "alt_name": null,
    "short_name": null,
    "official_name": null
  },
  {
    "country": "CA",
    "state_abbr": "NB",
    "state_name": "New Brunswick",
    "name": "Île à William",
    "osm_type": "way",
    "osm_id": 697011520,
    "admin_level": "9",
    "level_name": "Wards/Districts",
    "wikidata": null,
    "fips": null,
    "alt_name": null,
    "short_name": null,
    "official_name": null
  },
  {
    "country": "CA",
    "state_abbr": "NB",
    "state_name": "New Brunswick",
    "name": "Bird Island",
    "osm_type": "way",
    "osm_id": 697020747,
    "admin_level": "9",
    "level_name": "Wards/Districts",
    "wikidata": null,
    "fips": null,
    "alt_name": null,
    "short_name": null,
    "official_name": null
  },
  {
    "country": "CA",
    "state_abbr": "NB",
    "state_name": "New Brunswick",
    "name": "Hospital Island",
    "osm_type": "way",
    "osm_id": 697020748,
    "admin_level": "9",
    "level_name": "Wards/Districts",
    "wikidata": null,
    "fips": null,
    "alt_name": null,
    "short_name": null,
    "official_name": null
  },
  {
    "country": "CA",
    "state_abbr": "NB",
    "state_name": "New Brunswick",
    "name": "Dicks Island",
    "osm_type": "way",
    "osm_id": 697020749,
    "admin_level": "9",
    "level_name": "Wards/Districts",
    "wikidata": null,
    "fips": null,
    "alt_name": null,
    "short_name": null,
    "official_name": null
  },
  {
    "country": "CA",
    "state_abbr": "NB",
    "state_name": "New Brunswick",
    "name": "Hog Island",
    "osm_type": "way",
    "osm_id": 697020752,
    "admin_level": "9",
    "level_name": "Wards/Districts",
    "wikidata": null,
    "fips": null,
    "alt_name": null,
    "short_name": null,
    "official_name": null
  },
  {
    "country": "CA",
    "state_abbr": "NB",
    "state_name": "New Brunswick",
    "name": "Hardwood Island",
    "osm_type": "way",
    "osm_id": 697020753,
    "admin_level": "9",
    "level_name": "Wards/Districts",
    "wikidata": null,
    "fips": null,
    "alt_name": null,
    "short_name": null,
    "official_name": null
  },
  {
    "country": "CA",
    "state_abbr": "NB",
    "state_name": "New Brunswick",
    "name": "Long Island",
    "osm_type": "way",
    "osm_id": 697020754,
    "admin_level": "9",
    "level_name": "Wards/Districts",
    "wikidata": null,
    "fips": null,
    "alt_name": null,
    "short_name": null,
    "official_name": null
  },
  {
    "country": "CA",
    "state_abbr": "NB",
    "state_name": "New Brunswick",
    "name": "Île du Portage",
    "osm_type": "way",
    "osm_id": 697023332,
    "admin_level": "9",
    "level_name": "Wards/Districts",
    "wikidata": null,
    "fips": null,
    "alt_name": null,
    "short_name": null,
    "official_name": null
  },
  {
    "country": "CA",
    "state_abbr": "NB",
    "state_name": "New Brunswick",
    "name": "New River Island",
    "osm_type": "way",
    "osm_id": 697042234,
    "admin_level": "9",
    "level_name": "Wards/Districts",
    "wikidata": null,
    "fips": null,
    "alt_name": null,
    "short_name": null,
    "official_name": null
  },
  {
    "country": "CA",
    "state_abbr": "NB",
    "state_name": "New Brunswick",
    "name": null,
    "osm_type": "way",
    "osm_id": 697878971,
    "admin_level": "9",
    "level_name": "Wards/Districts",
    "wikidata": null,
    "fips": null,
    "alt_name": null,
    "short_name": null,
    "official_name": null
  },
  {
    "country": "CA",
    "state_abbr": "NB",
    "state_name": "New Brunswick",
    "name": "Duck Islands",
    "osm_type": "way",
    "osm_id": 697878972,
    "admin_level": "9",
    "level_name": "Wards/Districts",
    "wikidata": null,
    "fips": null,
    "alt_name": null,
    "short_name": null,
    "official_name": null
  },
  {
    "country": "CA",
    "state_abbr": "NB",
    "state_name": "New Brunswick",
    "name": "Duck Islands",
    "osm_type": "way",
    "osm_id": 697878973,
    "admin_level": "9",
    "level_name": "Wards/Districts",
    "wikidata": null,
    "fips": null,
    "alt_name": null,
    "short_name": null,
    "official_name": null
  },
  {
    "country": "CA",
    "state_abbr": "NB",
    "state_name": "New Brunswick",
    "name": "Gooseberry Island",
    "osm_type": "way",
    "osm_id": 697881262,
    "admin_level": "9",
    "level_name": "Wards/Districts",
    "wikidata": null,
    "fips": null,
    "alt_name": null,
    "short_name": null,
    "official_name": null
  },
  {
    "country": "CA",
    "state_abbr": "NB",
    "state_name": "New Brunswick",
    "name": "Manawagonish Island",
    "osm_type": "way",
    "osm_id": 697888004,
    "admin_level": "9",
    "level_name": "Wards/Districts",
    "wikidata": null,
    "fips": null,
    "alt_name": null,
    "short_name": null,
    "official_name": null
  },
  {
    "country": "CA",
    "state_abbr": "NB",
    "state_name": "New Brunswick",
    "name": "Thumb Cap",
    "osm_type": "way",
    "osm_id": 697888897,
    "admin_level": "9",
    "level_name": "Wards/Districts",
    "wikidata": null,
    "fips": null,
    "alt_name": null,
    "short_name": null,
    "official_name": null
  },
  {
    "country": "CA",
    "state_abbr": "NB",
    "state_name": "New Brunswick",
    "name": "Île-au-Crâne",
    "osm_type": "way",
    "osm_id": 698033288,
    "admin_level": "9",
    "level_name": "Wards/Districts",
    "wikidata": null,
    "fips": null,
    "alt_name": null,
    "short_name": null,
    "official_name": null
  },
  {
    "country": "CA",
    "state_abbr": "NB",
    "state_name": "New Brunswick",
    "name": null,
    "osm_type": "way",
    "osm_id": 993207282,
    "admin_level": "9",
    "level_name": "Wards/Districts",
    "wikidata": null,
    "fips": null,
    "alt_name": null,
    "short_name": null,
    "official_name": null
  },
  {
    "country": "CA",
    "state_abbr": "NB",
    "state_name": "New Brunswick",
    "name": "Bliss Island",
    "osm_type": "way",
    "osm_id": 1387346903,
    "admin_level": "9",
    "level_name": "Wards/Districts",
    "wikidata": null,
    "fips": null,
    "alt_name": null,
    "short_name": null,
    "official_name": null
  },
  {
    "country": "CA",
    "state_abbr": "NB",
    "state_name": "New Brunswick",
    "name": "Bliss Island",
    "osm_type": "way",
    "osm_id": 1387346914,
    "admin_level": "9",
    "level_name": "Wards/Districts",
    "wikidata": null,
    "fips": null,
    "alt_name": null,
    "short_name": null,
    "official_name": null
  },
  {
    "country": "CA",
    "state_abbr": "NB",
    "state_name": "New Brunswick",
    "name": "Bliss Island",
    "osm_type": "way",
    "osm_id": 1387346916,
    "admin_level": "9",
    "level_name": "Wards/Districts",
    "wikidata": null,
    "fips": null,
    "alt_name": null,
    "short_name": null,
    "official_name": null
  },
  {
    "country": "CA",
    "state_abbr": "NB",
    "state_name": "New Brunswick",
    "name": "Bliss Island",
    "osm_type": "way",
    "osm_id": 1387346917,
    "admin_level": "9",
    "level_name": "Wards/Districts",
    "wikidata": null,
    "fips": null,
    "alt_name": null,
    "short_name": null,
    "official_name": null
  },
  {
    "country": "CA",
    "state_abbr": "NB",
    "state_name": "New Brunswick",
    "name": "Bliss Island",
    "osm_type": "way",
    "osm_id": 1387346919,
    "admin_level": "9",
    "level_name": "Wards/Districts",
    "wikidata": null,
    "fips": null,
    "alt_name": null,
    "short_name": null,
    "official_name": null
  },
  {
    "country": "CA",
    "state_abbr": "NB",
    "state_name": "New Brunswick",
    "name": "Bliss Island",
    "osm_type": "way",
    "osm_id": 1387346920,
    "admin_level": "9",
    "level_name": "Wards/Districts",
    "wikidata": null,
    "fips": null,
    "alt_name": null,
    "short_name": null,
    "official_name": null
  },
  {
    "country": "CA",
    "state_abbr": "NB",
    "state_name": "New Brunswick",
    "name": "Bliss Island",
    "osm_type": "way",
    "osm_id": 1387346921,
    "admin_level": "9",
    "level_name": "Wards/Districts",
    "wikidata": null,
    "fips": null,
    "alt_name": null,
    "short_name": null,
    "official_name": null
  },
  {
    "country": "CA",
    "state_abbr": "NB",
    "state_name": "New Brunswick",
    "name": "Bliss Island",
    "osm_type": "way",
    "osm_id": 1387346925,
    "admin_level": "9",
    "level_name": "Wards/Districts",
    "wikidata": null,
    "fips": null,
    "alt_name": null,
    "short_name": null,
    "official_name": null
  },
  {
    "country": "CA",
    "state_abbr": "NB",
    "state_name": "New Brunswick",
    "name": "Bliss Island",
    "osm_type": "way",
    "osm_id": 1387346926,
    "admin_level": "9",
    "level_name": "Wards/Districts",
    "wikidata": null,
    "fips": null,
    "alt_name": null,
    "short_name": null,
    "official_name": null
  },
  {
    "country": "CA",
    "state_abbr": "NB",
    "state_name": "New Brunswick",
    "name": "Barnes Island",
    "osm_type": "way",
    "osm_id": 1388301457,
    "admin_level": "9",
    "level_name": "Wards/Districts",
    "wikidata": null,
    "fips": null,
    "alt_name": null,
    "short_name": null,
    "official_name": null
  },
  {
    "country": "CA",
    "state_abbr": "NB",
    "state_name": "New Brunswick",
    "name": "Barnes Island",
    "osm_type": "way",
    "osm_id": 1388301458,
    "admin_level": "9",
    "level_name": "Wards/Districts",
    "wikidata": null,
    "fips": null,
    "alt_name": null,
    "short_name": null,
    "official_name": null
  },
  {
    "country": "CA",
    "state_abbr": "NB",
    "state_name": "New Brunswick",
    "name": "Barnes Island",
    "osm_type": "way",
    "osm_id": 1388301459,
    "admin_level": "9",
    "level_name": "Wards/Districts",
    "wikidata": null,
    "fips": null,
    "alt_name": null,
    "short_name": null,
    "official_name": null
  },
  {
    "country": "CA",
    "state_abbr": "NB",
    "state_name": "New Brunswick",
    "name": "Mowat Island",
    "osm_type": "relation",
    "osm_id": 9674303,
    "admin_level": "9",
    "level_name": "Wards/Districts",
    "wikidata": null,
    "fips": null,
    "alt_name": null,
    "short_name": null,
    "official_name": null
  },
  {
    "country": "CA",
    "state_abbr": "NB",
    "state_name": "New Brunswick",
    "name": "Indian Island",
    "osm_type": "relation",
    "osm_id": 9674306,
    "admin_level": "9",
    "level_name": "Wards/Districts",
    "wikidata": null,
    "fips": null,
    "alt_name": null,
    "short_name": null,
    "official_name": null
  },
  {
    "country": "CA",
    "state_abbr": "NB",
    "state_name": "New Brunswick",
    "name": "Cosco Bay Island",
    "osm_type": "relation",
    "osm_id": 9674307,
    "admin_level": "9",
    "level_name": "Wards/Districts",
    "wikidata": null,
    "fips": null,
    "alt_name": null,
    "short_name": null,
    "official_name": null
  },
  {
    "country": "CA",
    "state_abbr": "NB",
    "state_name": "New Brunswick",
    "name": "Jameson Island",
    "osm_type": "relation",
    "osm_id": 9674308,
    "admin_level": "9",
    "level_name": "Wards/Districts",
    "wikidata": null,
    "fips": null,
    "alt_name": null,
    "short_name": null,
    "official_name": null
  },
  {
    "country": "CA",
    "state_abbr": "NB",
    "state_name": "New Brunswick",
    "name": "Macs Island",
    "osm_type": "relation",
    "osm_id": 9674309,
    "admin_level": "9",
    "level_name": "Wards/Districts",
    "wikidata": null,
    "fips": null,
    "alt_name": null,
    "short_name": null,
    "official_name": null
  },
  {
    "country": "CA",
    "state_abbr": "NB",
    "state_name": "New Brunswick",
    "name": "Parker Island",
    "osm_type": "relation",
    "osm_id": 9674310,
    "admin_level": "9",
    "level_name": "Wards/Districts",
    "wikidata": null,
    "fips": null,
    "alt_name": null,
    "short_name": null,
    "official_name": null
  },
  {
    "country": "CA",
    "state_abbr": "NB",
    "state_name": "New Brunswick",
    "name": "Barnes Island",
    "osm_type": "relation",
    "osm_id": 9674311,
    "admin_level": "9",
    "level_name": "Wards/Districts",
    "wikidata": null,
    "fips": null,
    "alt_name": null,
    "short_name": null,
    "official_name": null
  },
  {
    "country": "CA",
    "state_abbr": "NB",
    "state_name": "New Brunswick",
    "name": "Spurce Island",
    "osm_type": "relation",
    "osm_id": 9674312,
    "admin_level": "9",
    "level_name": "Wards/Districts",
    "wikidata": null,
    "fips": null,
    "alt_name": null,
    "short_name": null,
    "official_name": null
  },
  {
    "country": "CA",
    "state_abbr": "NB",
    "state_name": "New Brunswick",
    "name": "Simpsons Island",
    "osm_type": "relation",
    "osm_id": 9674313,
    "admin_level": "9",
    "level_name": "Wards/Districts",
    "wikidata": null,
    "fips": null,
    "alt_name": null,
    "short_name": null,
    "official_name": null
  },
  {
    "country": "CA",
    "state_abbr": "NB",
    "state_name": "New Brunswick",
    "name": "St. Helena Island",
    "osm_type": "relation",
    "osm_id": 9674314,
    "admin_level": "9",
    "level_name": "Wards/Districts",
    "wikidata": null,
    "fips": null,
    "alt_name": null,
    "short_name": null,
    "official_name": null
  },
  {
    "country": "CA",
    "state_abbr": "NB",
    "state_name": "New Brunswick",
    "name": "Beans Island",
    "osm_type": "relation",
    "osm_id": 9674315,
    "admin_level": "9",
    "level_name": "Wards/Districts",
    "wikidata": null,
    "fips": null,
    "alt_name": null,
    "short_name": null,
    "official_name": null
  },
  {
    "country": "CA",
    "state_abbr": "NB",
    "state_name": "New Brunswick",
    "name": "Navy Island",
    "osm_type": "relation",
    "osm_id": 9680104,
    "admin_level": "9",
    "level_name": "Wards/Districts",
    "wikidata": null,
    "fips": null,
    "alt_name": null,
    "short_name": null,
    "official_name": null
  },
  {
    "country": "CA",
    "state_abbr": "NB",
    "state_name": "New Brunswick",
    "name": "Ministers Island",
    "osm_type": "relation",
    "osm_id": 9680105,
    "admin_level": "9",
    "level_name": "Wards/Districts",
    "wikidata": null,
    "fips": null,
    "alt_name": null,
    "short_name": null,
    "official_name": null
  },
  {
    "country": "CA",
    "state_abbr": "NB",
    "state_name": "New Brunswick",
    "name": "Heron Island",
    "osm_type": "relation",
    "osm_id": 9682194,
    "admin_level": "9",
    "level_name": "Wards/Districts",
    "wikidata": null,
    "fips": null,
    "alt_name": null,
    "short_name": null,
    "official_name": null
  },
  {
    "country": "CA",
    "state_abbr": "NB",
    "state_name": "New Brunswick",
    "name": "Hills Island",
    "osm_type": "relation",
    "osm_id": 9683850,
    "admin_level": "9",
    "level_name": "Wards/Districts",
    "wikidata": null,
    "fips": null,
    "alt_name": null,
    "short_name": null,
    "official_name": null
  },
  {
    "country": "CA",
    "state_abbr": "NB",
    "state_name": "New Brunswick",
    "name": "Flea island",
    "osm_type": "relation",
    "osm_id": 9683851,
    "admin_level": "9",
    "level_name": "Wards/Districts",
    "wikidata": null,
    "fips": null,
    "alt_name": null,
    "short_name": null,
    "official_name": null
  },
  {
    "country": "CA",
    "state_abbr": "NB",
    "state_name": "New Brunswick",
    "name": "Howards Island",
    "osm_type": "relation",
    "osm_id": 9683852,
    "admin_level": "9",
    "level_name": "Wards/Districts",
    "wikidata": "Q22646779",
    "fips": null,
    "alt_name": null,
    "short_name": null,
    "official_name": null
  },
  {
    "country": "CA",
    "state_abbr": "NB",
    "state_name": "New Brunswick",
    "name": "Five Island",
    "osm_type": "relation",
    "osm_id": 9683853,
    "admin_level": "9",
    "level_name": "Wards/Districts",
    "wikidata": null,
    "fips": null,
    "alt_name": null,
    "short_name": null,
    "official_name": null
  },
  {
    "country": "CA",
    "state_abbr": "NB",
    "state_name": "New Brunswick",
    "name": "Île à William",
    "osm_type": "relation",
    "osm_id": 9685788,
    "admin_level": "9",
    "level_name": "Wards/Districts",
    "wikidata": null,
    "fips": null,
    "alt_name": null,
    "short_name": null,
    "official_name": null
  },
  {
    "country": "CA",
    "state_abbr": "NB",
    "state_name": "New Brunswick",
    "name": "Hog Island",
    "osm_type": "relation",
    "osm_id": 9686126,
    "admin_level": "9",
    "level_name": "Wards/Districts",
    "wikidata": null,
    "fips": null,
    "alt_name": null,
    "short_name": null,
    "official_name": null
  },
  {
    "country": "CA",
    "state_abbr": "NB",
    "state_name": "New Brunswick",
    "name": "Île du Portage",
    "osm_type": "relation",
    "osm_id": 9686145,
    "admin_level": "9",
    "level_name": "Wards/Districts",
    "wikidata": null,
    "fips": null,
    "alt_name": null,
    "short_name": null,
    "official_name": null
  },
  {
    "country": "CA",
    "state_abbr": "NB",
    "state_name": "New Brunswick",
    "name": "Long Island",
    "osm_type": "relation",
    "osm_id": 9686158,
    "admin_level": "9",
    "level_name": "Wards/Districts",
    "wikidata": null,
    "fips": null,
    "alt_name": null,
    "short_name": null,
    "official_name": null
  },
  {
    "country": "CA",
    "state_abbr": "NB",
    "state_name": "New Brunswick",
    "name": "White Island",
    "osm_type": "relation",
    "osm_id": 9686421,
    "admin_level": "9",
    "level_name": "Wards/Districts",
    "wikidata": null,
    "fips": null,
    "alt_name": null,
    "short_name": null,
    "official_name": null
  },
  {
    "country": "CA",
    "state_abbr": "NB",
    "state_name": "New Brunswick",
    "name": "New River Island",
    "osm_type": "relation",
    "osm_id": 9686472,
    "admin_level": "9",
    "level_name": "Wards/Districts",
    "wikidata": null,
    "fips": null,
    "alt_name": null,
    "short_name": null,
    "official_name": null
  },
  {
    "country": "CA",
    "state_abbr": "NB",
    "state_name": "New Brunswick",
    "name": "Île de Cocagne",
    "osm_type": "relation",
    "osm_id": 9689214,
    "admin_level": "9",
    "level_name": "Wards/Districts",
    "wikidata": "Q22517519",
    "fips": null,
    "alt_name": null,
    "short_name": null,
    "official_name": null
  },
  {
    "country": "CA",
    "state_abbr": "NB",
    "state_name": "New Brunswick",
    "name": "Indian Island",
    "osm_type": "relation",
    "osm_id": 9689814,
    "admin_level": "9",
    "level_name": "Wards/Districts",
    "wikidata": null,
    "fips": null,
    "alt_name": null,
    "short_name": null,
    "official_name": null
  },
  {
    "country": "CA",
    "state_abbr": "NB",
    "state_name": "New Brunswick",
    "name": "Hardwood Island",
    "osm_type": "relation",
    "osm_id": 9692348,
    "admin_level": "9",
    "level_name": "Wards/Districts",
    "wikidata": null,
    "fips": null,
    "alt_name": null,
    "short_name": null,
    "official_name": null
  },
  {
    "country": "CA",
    "state_abbr": "NB",
    "state_name": "New Brunswick",
    "name": "Duck Islands",
    "osm_type": "relation",
    "osm_id": 9699063,
    "admin_level": "9",
    "level_name": "Wards/Districts",
    "wikidata": null,
    "fips": null,
    "alt_name": null,
    "short_name": null,
    "official_name": null
  },
  {
    "country": "CA",
    "state_abbr": "NB",
    "state_name": "New Brunswick",
    "name": "Gooseberry Island",
    "osm_type": "relation",
    "osm_id": 9699095,
    "admin_level": "9",
    "level_name": "Wards/Districts",
    "wikidata": null,
    "fips": null,
    "alt_name": null,
    "short_name": null,
    "official_name": null
  },
  {
    "country": "CA",
    "state_abbr": "NB",
    "state_name": "New Brunswick",
    "name": "Manawagonish Island",
    "osm_type": "relation",
    "osm_id": 9699160,
    "admin_level": "9",
    "level_name": "Wards/Districts",
    "wikidata": null,
    "fips": null,
    "alt_name": null,
    "short_name": null,
    "official_name": null
  },
  {
    "country": "CA",
    "state_abbr": "NB",
    "state_name": "New Brunswick",
    "name": "Thumb Cap",
    "osm_type": "relation",
    "osm_id": 9699165,
    "admin_level": "9",
    "level_name": "Wards/Districts",
    "wikidata": null,
    "fips": null,
    "alt_name": null,
    "short_name": null,
    "official_name": null
  },
  {
    "country": "CA",
    "state_abbr": "NB",
    "state_name": "New Brunswick",
    "name": "Île de Shédiac",
    "osm_type": "relation",
    "osm_id": 9700420,
    "admin_level": "9",
    "level_name": "Wards/Districts",
    "wikidata": "Q3593413",
    "fips": null,
    "alt_name": null,
    "short_name": null,
    "official_name": null
  },
  {
    "country": "CA",
    "state_abbr": "NB",
    "state_name": "New Brunswick",
    "name": "Skull Island",
    "osm_type": "relation",
    "osm_id": 9700425,
    "admin_level": "9",
    "level_name": "Wards/Districts",
    "wikidata": null,
    "fips": null,
    "alt_name": null,
    "short_name": null,
    "official_name": null
  },
  {
    "country": "CA",
    "state_abbr": "NB",
    "state_name": "New Brunswick",
    "name": "Cull Island",
    "osm_type": "relation",
    "osm_id": 9701376,
    "admin_level": "9",
    "level_name": "Wards/Districts",
    "wikidata": null,
    "fips": null,
    "alt_name": null,
    "short_name": null,
    "official_name": null
  },
  {
    "country": "CA",
    "state_abbr": "NB",
    "state_name": "New Brunswick",
    "name": "Sheep Island",
    "osm_type": "relation",
    "osm_id": 9701377,
    "admin_level": "9",
    "level_name": "Wards/Districts",
    "wikidata": null,
    "fips": null,
    "alt_name": null,
    "short_name": null,
    "official_name": null
  },
  {
    "country": "CA",
    "state_abbr": "NB",
    "state_name": "New Brunswick",
    "name": "Pumpkin Islet",
    "osm_type": "relation",
    "osm_id": 9701378,
    "admin_level": "9",
    "level_name": "Wards/Districts",
    "wikidata": null,
    "fips": null,
    "alt_name": null,
    "short_name": null,
    "official_name": null
  },
  {
    "country": "CA",
    "state_abbr": "NB",
    "state_name": "New Brunswick",
    "name": "South Green Island",
    "osm_type": "relation",
    "osm_id": 9701379,
    "admin_level": "9",
    "level_name": "Wards/Districts",
    "wikidata": null,
    "fips": null,
    "alt_name": null,
    "short_name": null,
    "official_name": null
  },
  {
    "country": "CA",
    "state_abbr": "NB",
    "state_name": "New Brunswick",
    "name": "Morans Island",
    "osm_type": "relation",
    "osm_id": 9701381,
    "admin_level": "9",
    "level_name": "Wards/Districts",
    "wikidata": null,
    "fips": null,
    "alt_name": null,
    "short_name": null,
    "official_name": null
  },
  {
    "country": "CA",
    "state_abbr": "NB",
    "state_name": "New Brunswick",
    "name": "Wood Island",
    "osm_type": "relation",
    "osm_id": 9701382,
    "admin_level": "9",
    "level_name": "Wards/Districts",
    "wikidata": null,
    "fips": null,
    "alt_name": null,
    "short_name": null,
    "official_name": null
  },
  {
    "country": "CA",
    "state_abbr": "NB",
    "state_name": "New Brunswick",
    "name": "White Horse Islet",
    "osm_type": "relation",
    "osm_id": 9701383,
    "admin_level": "9",
    "level_name": "Wards/Districts",
    "wikidata": null,
    "fips": null,
    "alt_name": null,
    "short_name": null,
    "official_name": null
  },
  {
    "country": "CA",
    "state_abbr": "NB",
    "state_name": "New Brunswick",
    "name": "High Duck Island",
    "osm_type": "relation",
    "osm_id": 9701408,
    "admin_level": "9",
    "level_name": "Wards/Districts",
    "wikidata": null,
    "fips": null,
    "alt_name": null,
    "short_name": null,
    "official_name": null
  },
  {
    "country": "CA",
    "state_abbr": "NB",
    "state_name": "New Brunswick",
    "name": "Ross Island",
    "osm_type": "relation",
    "osm_id": 9701409,
    "admin_level": "9",
    "level_name": "Wards/Districts",
    "wikidata": null,
    "fips": null,
    "alt_name": null,
    "short_name": null,
    "official_name": null
  },
  {
    "country": "CA",
    "state_abbr": "NB",
    "state_name": "New Brunswick",
    "name": "North Green Island",
    "osm_type": "relation",
    "osm_id": 9701413,
    "admin_level": "9",
    "level_name": "Wards/Districts",
    "wikidata": null,
    "fips": null,
    "alt_name": null,
    "short_name": null,
    "official_name": null
  },
  {
    "country": "CA",
    "state_abbr": "NB",
    "state_name": "New Brunswick",
    "name": "West Pumpkin Island",
    "osm_type": "relation",
    "osm_id": 9701416,
    "admin_level": "9",
    "level_name": "Wards/Districts",
    "wikidata": null,
    "fips": null,
    "alt_name": null,
    "short_name": null,
    "official_name": null
  },
  {
    "country": "CA",
    "state_abbr": "NB",
    "state_name": "New Brunswick",
    "name": "Hay Island",
    "osm_type": "relation",
    "osm_id": 9701466,
    "admin_level": "9",
    "level_name": "Wards/Districts",
    "wikidata": null,
    "fips": null,
    "alt_name": null,
    "short_name": null,
    "official_name": null
  },
  {
    "country": "CA",
    "state_abbr": "NB",
    "state_name": "New Brunswick",
    "name": "Kent Island",
    "osm_type": "relation",
    "osm_id": 9701467,
    "admin_level": "9",
    "level_name": "Wards/Districts",
    "wikidata": null,
    "fips": null,
    "alt_name": null,
    "short_name": null,
    "official_name": null
  },
  {
    "country": "CA",
    "state_abbr": "NB",
    "state_name": "New Brunswick",
    "name": "Nub Island",
    "osm_type": "relation",
    "osm_id": 9701969,
    "admin_level": "9",
    "level_name": "Wards/Districts",
    "wikidata": null,
    "fips": null,
    "alt_name": null,
    "short_name": null,
    "official_name": null
  },
  {
    "country": "CA",
    "state_abbr": "NB",
    "state_name": "New Brunswick",
    "name": "Bar Island",
    "osm_type": "relation",
    "osm_id": 9701970,
    "admin_level": "9",
    "level_name": "Wards/Districts",
    "wikidata": null,
    "fips": null,
    "alt_name": null,
    "short_name": null,
    "official_name": null
  },
  {
    "country": "CA",
    "state_abbr": "NB",
    "state_name": "New Brunswick",
    "name": "Hospital Islands",
    "osm_type": "relation",
    "osm_id": 9701971,
    "admin_level": "9",
    "level_name": "Wards/Districts",
    "wikidata": null,
    "fips": null,
    "alt_name": null,
    "short_name": null,
    "official_name": null
  },
  {
    "country": "CA",
    "state_abbr": "NB",
    "state_name": "New Brunswick",
    "name": "Tinkers Island",
    "osm_type": "relation",
    "osm_id": 9701972,
    "admin_level": "9",
    "level_name": "Wards/Districts",
    "wikidata": null,
    "fips": null,
    "alt_name": null,
    "short_name": null,
    "official_name": null
  },
  {
    "country": "CA",
    "state_abbr": "NB",
    "state_name": "New Brunswick",
    "name": "White Horse Island",
    "osm_type": "relation",
    "osm_id": 9701973,
    "admin_level": "9",
    "level_name": "Wards/Districts",
    "wikidata": null,
    "fips": null,
    "alt_name": null,
    "short_name": null,
    "official_name": null
  },
  {
    "country": "CA",
    "state_abbr": "NB",
    "state_name": "New Brunswick",
    "name": "The Pup",
    "osm_type": "relation",
    "osm_id": 9701977,
    "admin_level": "9",
    "level_name": "Wards/Districts",
    "wikidata": null,
    "fips": null,
    "alt_name": null,
    "short_name": null,
    "official_name": null
  },
  {
    "country": "CA",
    "state_abbr": "NB",
    "state_name": "New Brunswick",
    "name": "Adam Island",
    "osm_type": "relation",
    "osm_id": 9701978,
    "admin_level": "9",
    "level_name": "Wards/Districts",
    "wikidata": null,
    "fips": null,
    "alt_name": null,
    "short_name": null,
    "official_name": null
  },
  {
    "country": "CA",
    "state_abbr": "NB",
    "state_name": "New Brunswick",
    "name": "Crow Island",
    "osm_type": "relation",
    "osm_id": 9701979,
    "admin_level": "9",
    "level_name": "Wards/Districts",
    "wikidata": null,
    "fips": null,
    "alt_name": null,
    "short_name": null,
    "official_name": null
  },
  {
    "country": "CA",
    "state_abbr": "NB",
    "state_name": "New Brunswick",
    "name": "New Ireland",
    "osm_type": "relation",
    "osm_id": 9701980,
    "admin_level": "9",
    "level_name": "Wards/Districts",
    "wikidata": null,
    "fips": null,
    "alt_name": null,
    "short_name": null,
    "official_name": null
  },
  {
    "country": "CA",
    "state_abbr": "NB",
    "state_name": "New Brunswick",
    "name": "Popes Island",
    "osm_type": "relation",
    "osm_id": 9701981,
    "admin_level": "9",
    "level_name": "Wards/Districts",
    "wikidata": null,
    "fips": null,
    "alt_name": null,
    "short_name": null,
    "official_name": null
  },
  {
    "country": "CA",
    "state_abbr": "NB",
    "state_name": "New Brunswick",
    "name": "Thumb Cap",
    "osm_type": "relation",
    "osm_id": 9701982,
    "admin_level": "9",
    "level_name": "Wards/Districts",
    "wikidata": null,
    "fips": null,
    "alt_name": null,
    "short_name": null,
    "official_name": null
  },
  {
    "country": "CA",
    "state_abbr": "NB",
    "state_name": "New Brunswick",
    "name": "The Nubble",
    "osm_type": "relation",
    "osm_id": 9701983,
    "admin_level": "9",
    "level_name": "Wards/Districts",
    "wikidata": null,
    "fips": null,
    "alt_name": null,
    "short_name": null,
    "official_name": null
  },
  {
    "country": "CA",
    "state_abbr": "NB",
    "state_name": "New Brunswick",
    "name": "Man of War Island",
    "osm_type": "relation",
    "osm_id": 9704004,
    "admin_level": "9",
    "level_name": "Wards/Districts",
    "wikidata": null,
    "fips": null,
    "alt_name": null,
    "short_name": null,
    "official_name": null
  },
  {
    "country": "CA",
    "state_abbr": "NB",
    "state_name": "New Brunswick",
    "name": "Eagle Island",
    "osm_type": "relation",
    "osm_id": 9704005,
    "admin_level": "9",
    "level_name": "Wards/Districts",
    "wikidata": null,
    "fips": null,
    "alt_name": null,
    "short_name": null,
    "official_name": null
  },
  {
    "country": "CA",
    "state_abbr": "NB",
    "state_name": "New Brunswick",
    "name": "Spruce Island",
    "osm_type": "relation",
    "osm_id": 9704006,
    "admin_level": "9",
    "level_name": "Wards/Districts",
    "wikidata": null,
    "fips": null,
    "alt_name": null,
    "short_name": null,
    "official_name": null
  },
  {
    "country": "CA",
    "state_abbr": "NB",
    "state_name": "New Brunswick",
    "name": "White Head Island",
    "osm_type": "relation",
    "osm_id": 9704007,
    "admin_level": "9",
    "level_name": "Wards/Districts",
    "wikidata": null,
    "fips": null,
    "alt_name": null,
    "short_name": null,
    "official_name": null
  },
  {
    "country": "CA",
    "state_abbr": "NB",
    "state_name": "New Brunswick",
    "name": "Bird Island",
    "osm_type": "relation",
    "osm_id": 9704610,
    "admin_level": "9",
    "level_name": "Wards/Districts",
    "wikidata": null,
    "fips": null,
    "alt_name": null,
    "short_name": null,
    "official_name": null
  },
  {
    "country": "CA",
    "state_abbr": "NB",
    "state_name": "New Brunswick",
    "name": "Hardwood Island",
    "osm_type": "relation",
    "osm_id": 9704613,
    "admin_level": "9",
    "level_name": "Wards/Districts",
    "wikidata": null,
    "fips": null,
    "alt_name": null,
    "short_name": null,
    "official_name": null
  },
  {
    "country": "CA",
    "state_abbr": "NB",
    "state_name": "New Brunswick",
    "name": "Hospital Island",
    "osm_type": "relation",
    "osm_id": 9704614,
    "admin_level": "9",
    "level_name": "Wards/Districts",
    "wikidata": null,
    "fips": null,
    "alt_name": null,
    "short_name": null,
    "official_name": null
  },
  {
    "country": "CA",
    "state_abbr": "NB",
    "state_name": "New Brunswick",
    "name": "Dicks Island",
    "osm_type": "relation",
    "osm_id": 9704615,
    "admin_level": "9",
    "level_name": "Wards/Districts",
    "wikidata": null,
    "fips": null,
    "alt_name": null,
    "short_name": null,
    "official_name": null
  },
  {
    "country": "CA",
    "state_abbr": "NB",
    "state_name": "New Brunswick",
    "name": "Green Island",
    "osm_type": "relation",
    "osm_id": 13332059,
    "admin_level": "9",
    "level_name": "Wards/Districts",
    "wikidata": null,
    "fips": null,
    "alt_name": null,
    "short_name": null,
    "official_name": null
  },
  {
    "country": "CA",
    "state_abbr": "NB",
    "state_name": "New Brunswick",
    "name": "Head Harbour Island",
    "osm_type": "relation",
    "osm_id": 13332233,
    "admin_level": "9",
    "level_name": "Wards/Districts",
    "wikidata": null,
    "fips": null,
    "alt_name": null,
    "short_name": null,
    "official_name": null
  },
  {
    "country": "CA",
    "state_abbr": "NB",
    "state_name": "New Brunswick",
    "name": "Partridge Island",
    "osm_type": "relation",
    "osm_id": 13334889,
    "admin_level": "9",
    "level_name": "Wards/Districts",
    "wikidata": null,
    "fips": null,
    "alt_name": null,
    "short_name": null,
    "official_name": null
  },
  {
    "country": "CA",
    "state_abbr": "NB",
    "state_name": "New Brunswick",
    "name": "Île de Shédiac",
    "osm_type": "relation",
    "osm_id": 16070079,
    "admin_level": "9",
    "level_name": "Wards/Districts",
    "wikidata": null,
    "fips": null,
    "alt_name": null,
    "short_name": null,
    "official_name": null
  }
]