[
  {
    "country": "US",
    "state_abbr": "TN",
    "state_name": "Tennessee",
    "name": "Tazewell City Limits",
    "osm_type": "way",
    "osm_id": 339582791,
    "admin_level": "10",
    "level_name": "Neighborhoods/Hamlets",
    "wikidata": null,
    "fips": null,
    "alt_name": null,
    "short_name": null,
    "official_name": null
  },
  {
    "country": "US",
    "state_abbr": "TN",
    "state_name": "Tennessee",
    "name": "Cedar Bluff",
    "osm_type": "way",
    "osm_id": 925611808,
    "admin_level": "10",
    "level_name": "Neighborhoods/Hamlets",
    "wikidata": null,
    "fips": null,
    "alt_name": null,
    "short_name": null,
    "official_name": null
  },
  {
    "country": "US",
    "state_abbr": "TN",
    "state_name": "Tennessee",
    "name": "Cedar Bluff",
    "osm_type": "way",
    "osm_id": 925611809,
    "admin_level": "10",
    "level_name": "Neighborhoods/Hamlets",
    "wikidata": null,
    "fips": null,
    "alt_name": null,
    "short_name": null,
    "official_name": null
  },
  {
    "country": "US",
    "state_abbr": "TN",
    "state_name": "Tennessee",
    "name": "West Hills",
    "osm_type": "way",
    "osm_id": 925624839,
    "admin_level": "10",
    "level_name": "Neighborhoods/Hamlets",
    "wikidata": null,
    "fips": null,
    "alt_name": null,
    "short_name": null,
    "official_name": null
  },
  {
    "country": "US",
    "state_abbr": "TN",
    "state_name": "Tennessee",
    "name": "Westwood",
    "osm_type": "way",
    "osm_id": 952399343,
    "admin_level": "10",
    "level_name": "Neighborhoods/Hamlets",
    "wikidata": null,
    "fips": null,
    "alt_name": null,
    "short_name": null,
    "official_name": null
  },
  {
    "country": "US",
    "state_abbr": "TN",
    "state_name": "Tennessee",
    "name": "Sutherland Heights",
    "osm_type": "way",
    "osm_id": 952399344,
    "admin_level": "10",
    "level_name": "Neighborhoods/Hamlets",
    "wikidata": null,
    "fips": null,
    "alt_name": null,
    "short_name": null,
    "official_name": null
  },
  {
    "country": "US",
    "state_abbr": "TN",
    "state_name": "Tennessee",
    "name": "Seqouyah Hills",
    "osm_type": "way",
    "osm_id": 952399346,
    "admin_level": "10",
    "level_name": "Neighborhoods/Hamlets",
    "wikidata": null,
    "fips": null,
    "alt_name": null,
    "short_name": null,
    "official_name": null
  },
  {
    "country": "US",
    "state_abbr": "TN",
    "state_name": "Tennessee",
    "name": "Parkridge",
    "osm_type": "way",
    "osm_id": 956671418,
    "admin_level": "10",
    "level_name": "Neighborhoods/Hamlets",
    "wikidata": null,
    "fips": null,
    "alt_name": null,
    "short_name": null,
    "official_name": null
  },
  {
    "country": "US",
    "state_abbr": "TN",
    "state_name": "Tennessee",
    "name": "Holston Hills",
    "osm_type": "way",
    "osm_id": 956671419,
    "admin_level": "10",
    "level_name": "Neighborhoods/Hamlets",
    "wikidata": null,
    "fips": null,
    "alt_name": null,
    "short_name": null,
    "official_name": null
  },
  {
    "country": "US",
    "state_abbr": "TN",
    "state_name": "Tennessee",
    "name": "Burlington",
    "osm_type": "way",
    "osm_id": 956671420,
    "admin_level": "10",
    "level_name": "Neighborhoods/Hamlets",
    "wikidata": null,
    "fips": null,
    "alt_name": null,
    "short_name": null,
    "official_name": null
  },
  {
    "country": "US",
    "state_abbr": "TN",
    "state_name": "Tennessee",
    "name": "Burlington",
    "osm_type": "way",
    "osm_id": 956671423,
    "admin_level": "10",
    "level_name": "Neighborhoods/Hamlets",
    "wikidata": null,
    "fips": null,
    "alt_name": null,
    "short_name": null,
    "official_name": null
  },
  {
    "country": "US",
    "state_abbr": "TN",
    "state_name": "Tennessee",
    "name": "Burlington",
    "osm_type": "way",
    "osm_id": 956671425,
    "admin_level": "10",
    "level_name": "Neighborhoods/Hamlets",
    "wikidata": null,
    "fips": null,
    "alt_name": null,
    "short_name": null,
    "official_name": null
  },
  {
    "country": "US",
    "state_abbr": "TN",
    "state_name": "Tennessee",
    "name": "Burlington",
    "osm_type": "way",
    "osm_id": 956671426,
    "admin_level": "10",
    "level_name": "Neighborhoods/Hamlets",
    "wikidata": null,
    "fips": null,
    "alt_name": null,
    "short_name": null,
    "official_name": null
  },
  {
    "country": "US",
    "state_abbr": "TN",
    "state_name": "Tennessee",
    "name": "Chilhowee Park",
    "osm_type": "way",
    "osm_id": 956671428,
    "admin_level": "10",
    "level_name": "Neighborhoods/Hamlets",
    "wikidata": null,
    "fips": null,
    "alt_name": null,
    "short_name": null,
    "official_name": null
  },
  {
    "country": "US",
    "state_abbr": "TN",
    "state_name": "Tennessee",
    "name": "Parkridge",
    "osm_type": "way",
    "osm_id": 956671429,
    "admin_level": "10",
    "level_name": "Neighborhoods/Hamlets",
    "wikidata": null,
    "fips": null,
    "alt_name": null,
    "short_name": null,
    "official_name": null
  },
  {
    "country": "US",
    "state_abbr": "TN",
    "state_name": "Tennessee",
    "name": "Parkridge",
    "osm_type": "way",
    "osm_id": 956671431,
    "admin_level": "10",
    "level_name": "Neighborhoods/Hamlets",
    "wikidata": null,
    "fips": null,
    "alt_name": null,
    "short_name": null,
    "official_name": null
  },
  {
    "country": "US",
    "state_abbr": "TN",
    "state_name": "Tennessee",
    "name": "Burlington",
    "osm_type": "way",
    "osm_id": 956671432,
    "admin_level": "10",
    "level_name": "Neighborhoods/Hamlets",
    "wikidata": null,
    "fips": null,
    "alt_name": null,
    "short_name": null,
    "official_name": null
  },
  {
    "country": "US",
    "state_abbr": "TN",
    "state_name": "Tennessee",
    "name": "Chilhowee Park",
    "osm_type": "way",
    "osm_id": 956671433,
    "admin_level": "10",
    "level_name": "Neighborhoods/Hamlets",
    "wikidata": null,
    "fips": null,
    "alt_name": null,
    "short_name": null,
    "official_name": null
  },
  {
    "country": "US",
    "state_abbr": "TN",
    "state_name": "Tennessee",
    "name": "Chilhowee Hills",
    "osm_type": "way",
    "osm_id": 956671435,
    "admin_level": "10",
    "level_name": "Neighborhoods/Hamlets",
    "wikidata": null,
    "fips": null,
    "alt_name": null,
    "short_name": null,
    "official_name": null
  },
  {
    "country": "US",
    "state_abbr": "TN",
    "state_name": "Tennessee",
    "name": "Holston Hills",
    "osm_type": "way",
    "osm_id": 956671436,
    "admin_level": "10",
    "level_name": "Neighborhoods/Hamlets",
    "wikidata": null,
    "fips": null,
    "alt_name": null,
    "short_name": null,
    "official_name": null
  },
  {
    "country": "US",
    "state_abbr": "TN",
    "state_name": "Tennessee",
    "name": "Burlington",
    "osm_type": "way",
    "osm_id": 956671439,
    "admin_level": "10",
    "level_name": "Neighborhoods/Hamlets",
    "wikidata": null,
    "fips": null,
    "alt_name": null,
    "short_name": null,
    "official_name": null
  },
  {
    "country": "US",
    "state_abbr": "TN",
    "state_name": "Tennessee",
    "name": "Holston Hills",
    "osm_type": "way",
    "osm_id": 956671442,
    "admin_level": "10",
    "level_name": "Neighborhoods/Hamlets",
    "wikidata": null,
    "fips": null,
    "alt_name": null,
    "short_name": null,
    "official_name": null
  },
  {
    "country": "US",
    "state_abbr": "TN",
    "state_name": "Tennessee",
    "name": "Chilhowee Hills",
    "osm_type": "way",
    "osm_id": 956676114,
    "admin_level": "10",
    "level_name": "Neighborhoods/Hamlets",
    "wikidata": null,
    "fips": null,
    "alt_name": null,
    "short_name": null,
    "official_name": null
  },
  {
    "country": "US",
    "state_abbr": "TN",
    "state_name": "Tennessee",
    "name": "Chilhowee Hills",
    "osm_type": "way",
    "osm_id": 956676116,
    "admin_level": "10",
    "level_name": "Neighborhoods/Hamlets",
    "wikidata": null,
    "fips": null,
    "alt_name": null,
    "short_name": null,
    "official_name": null
  },
  {
    "country": "US",
    "state_abbr": "TN",
    "state_name": "Tennessee",
    "name": "Fourth and Gill",
    "osm_type": "way",
    "osm_id": 957242507,
    "admin_level": "10",
    "level_name": "Neighborhoods/Hamlets",
    "wikidata": null,
    "fips": null,
    "alt_name": null,
    "short_name": null,
    "official_name": null
  },
  {
    "country": "US",
    "state_abbr": "TN",
    "state_name": "Tennessee",
    "name": "Parkridge",
    "osm_type": "way",
    "osm_id": 957242508,
    "admin_level": "10",
    "level_name": "Neighborhoods/Hamlets",
    "wikidata": null,
    "fips": null,
    "alt_name": null,
    "short_name": null,
    "official_name": null
  },
  {
    "country": "US",
    "state_abbr": "TN",
    "state_name": "Tennessee",
    "name": "University of Tennessee",
    "osm_type": "way",
    "osm_id": 957594041,
    "admin_level": "10",
    "level_name": "Neighborhoods/Hamlets",
    "wikidata": null,
    "fips": null,
    "alt_name": null,
    "short_name": null,
    "official_name": null
  },
  {
    "country": "US",
    "state_abbr": "TN",
    "state_name": "Tennessee",
    "name": "University of Tennessee",
    "osm_type": "way",
    "osm_id": 957594046,
    "admin_level": "10",
    "level_name": "Neighborhoods/Hamlets",
    "wikidata": null,
    "fips": null,
    "alt_name": null,
    "short_name": null,
    "official_name": null
  },
  {
    "country": "US",
    "state_abbr": "TN",
    "state_name": "Tennessee",
    "name": "University of Tennessee",
    "osm_type": "way",
    "osm_id": 957608135,
    "admin_level": "10",
    "level_name": "Neighborhoods/Hamlets",
    "wikidata": null,
    "fips": null,
    "alt_name": null,
    "short_name": null,
    "official_name": null
  },
  {
    "country": "US",
    "state_abbr": "TN",
    "state_name": "Tennessee",
    "name": "John Sevier",
    "osm_type": "way",
    "osm_id": 978522472,
    "admin_level": "10",
    "level_name": "Neighborhoods/Hamlets",
    "wikidata": null,
    "fips": null,
    "alt_name": null,
    "short_name": null,
    "official_name": null
  },
  {
    "country": "US",
    "state_abbr": "TN",
    "state_name": "Tennessee",
    "name": "John Sevier",
    "osm_type": "way",
    "osm_id": 978522474,
    "admin_level": "10",
    "level_name": "Neighborhoods/Hamlets",
    "wikidata": null,
    "fips": null,
    "alt_name": null,
    "short_name": null,
    "official_name": null
  },
  {
    "country": "US",
    "state_abbr": "TN",
    "state_name": "Tennessee",
    "name": "Tellico Village",
    "osm_type": "way",
    "osm_id": 1002710601,
    "admin_level": "10",
    "level_name": "Neighborhoods/Hamlets",
    "wikidata": null,
    "fips": null,
    "alt_name": null,
    "short_name": null,
    "official_name": null
  },
  {
    "country": "US",
    "state_abbr": "TN",
    "state_name": "Tennessee",
    "name": "Parkridge",
    "osm_type": "way",
    "osm_id": 1011098033,
    "admin_level": "10",
    "level_name": "Neighborhoods/Hamlets",
    "wikidata": null,
    "fips": null,
    "alt_name": null,
    "short_name": null,
    "official_name": null
  },
  {
    "country": "US",
    "state_abbr": "TN",
    "state_name": "Tennessee",
    "name": "Island Home",
    "osm_type": "way",
    "osm_id": 1016966483,
    "admin_level": "10",
    "level_name": "Neighborhoods/Hamlets",
    "wikidata": null,
    "fips": null,
    "alt_name": null,
    "short_name": null,
    "official_name": null
  },
  {
    "country": "US",
    "state_abbr": "TN",
    "state_name": "Tennessee",
    "name": "Bearden",
    "osm_type": "way",
    "osm_id": 1022343468,
    "admin_level": "10",
    "level_name": "Neighborhoods/Hamlets",
    "wikidata": null,
    "fips": null,
    "alt_name": null,
    "short_name": null,
    "official_name": null
  },
  {
    "country": "US",
    "state_abbr": "TN",
    "state_name": "Tennessee",
    "name": "Bearden",
    "osm_type": "way",
    "osm_id": 1022343469,
    "admin_level": "10",
    "level_name": "Neighborhoods/Hamlets",
    "wikidata": null,
    "fips": null,
    "alt_name": null,
    "short_name": null,
    "official_name": null
  },
  {
    "country": "US",
    "state_abbr": "TN",
    "state_name": "Tennessee",
    "name": "Seqouyah Hills",
    "osm_type": "way",
    "osm_id": 1022343471,
    "admin_level": "10",
    "level_name": "Neighborhoods/Hamlets",
    "wikidata": null,
    "fips": null,
    "alt_name": null,
    "short_name": null,
    "official_name": null
  },
  {
    "country": "US",
    "state_abbr": "TN",
    "state_name": "Tennessee",
    "name": "Bearden",
    "osm_type": "way",
    "osm_id": 1022343472,
    "admin_level": "10",
    "level_name": "Neighborhoods/Hamlets",
    "wikidata": null,
    "fips": null,
    "alt_name": null,
    "short_name": null,
    "official_name": null
  },
  {
    "country": "US",
    "state_abbr": "TN",
    "state_name": "Tennessee",
    "name": "West Hills",
    "osm_type": "way",
    "osm_id": 1022343473,
    "admin_level": "10",
    "level_name": "Neighborhoods/Hamlets",
    "wikidata": null,
    "fips": null,
    "alt_name": null,
    "short_name": null,
    "official_name": null
  },
  {
    "country": "US",
    "state_abbr": "TN",
    "state_name": "Tennessee",
    "name": "West Hills",
    "osm_type": "way",
    "osm_id": 1022343475,
    "admin_level": "10",
    "level_name": "Neighborhoods/Hamlets",
    "wikidata": null,
    "fips": null,
    "alt_name": null,
    "short_name": null,
    "official_name": null
  },
  {
    "country": "US",
    "state_abbr": "TN",
    "state_name": "Tennessee",
    "name": "Bearden",
    "osm_type": "way",
    "osm_id": 1022343476,
    "admin_level": "10",
    "level_name": "Neighborhoods/Hamlets",
    "wikidata": null,
    "fips": null,
    "alt_name": null,
    "short_name": null,
    "official_name": null
  },
  {
    "country": "US",
    "state_abbr": "TN",
    "state_name": "Tennessee",
    "name": "Marble City",
    "osm_type": "way",
    "osm_id": 1022343477,
    "admin_level": "10",
    "level_name": "Neighborhoods/Hamlets",
    "wikidata": null,
    "fips": null,
    "alt_name": null,
    "short_name": null,
    "official_name": null
  },
  {
    "country": "US",
    "state_abbr": "TN",
    "state_name": "Tennessee",
    "name": "University of Tennessee",
    "osm_type": "way",
    "osm_id": 1022343479,
    "admin_level": "10",
    "level_name": "Neighborhoods/Hamlets",
    "wikidata": null,
    "fips": null,
    "alt_name": null,
    "short_name": null,
    "official_name": null
  },
  {
    "country": "US",
    "state_abbr": "TN",
    "state_name": "Tennessee",
    "name": "Lake Forest",
    "osm_type": "way",
    "osm_id": 1026198498,
    "admin_level": "10",
    "level_name": "Neighborhoods/Hamlets",
    "wikidata": null,
    "fips": null,
    "alt_name": null,
    "short_name": null,
    "official_name": null
  },
  {
    "country": "US",
    "state_abbr": "TN",
    "state_name": "Tennessee",
    "name": "Colonial Village",
    "osm_type": "way",
    "osm_id": 1026198499,
    "admin_level": "10",
    "level_name": "Neighborhoods/Hamlets",
    "wikidata": null,
    "fips": null,
    "alt_name": null,
    "short_name": null,
    "official_name": null
  },
  {
    "country": "US",
    "state_abbr": "TN",
    "state_name": "Tennessee",
    "name": "Lake Forest",
    "osm_type": "way",
    "osm_id": 1026198502,
    "admin_level": "10",
    "level_name": "Neighborhoods/Hamlets",
    "wikidata": null,
    "fips": null,
    "alt_name": null,
    "short_name": null,
    "official_name": null
  },
  {
    "country": "US",
    "state_abbr": "TN",
    "state_name": "Tennessee",
    "name": "Colonial Village",
    "osm_type": "way",
    "osm_id": 1026198503,
    "admin_level": "10",
    "level_name": "Neighborhoods/Hamlets",
    "wikidata": null,
    "fips": null,
    "alt_name": null,
    "short_name": null,
    "official_name": null
  },
  {
    "country": "US",
    "state_abbr": "TN",
    "state_name": "Tennessee",
    "name": "Lake Forest",
    "osm_type": "way",
    "osm_id": 1026198505,
    "admin_level": "10",
    "level_name": "Neighborhoods/Hamlets",
    "wikidata": null,
    "fips": null,
    "alt_name": null,
    "short_name": null,
    "official_name": null
  },
  {
    "country": "US",
    "state_abbr": "TN",
    "state_name": "Tennessee",
    "name": "Island Home",
    "osm_type": "way",
    "osm_id": 1026198508,
    "admin_level": "10",
    "level_name": "Neighborhoods/Hamlets",
    "wikidata": null,
    "fips": null,
    "alt_name": null,
    "short_name": null,
    "official_name": null
  },
  {
    "country": "US",
    "state_abbr": "TN",
    "state_name": "Tennessee",
    "name": "University of Tennessee",
    "osm_type": "way",
    "osm_id": 1028729952,
    "admin_level": "10",
    "level_name": "Neighborhoods/Hamlets",
    "wikidata": null,
    "fips": null,
    "alt_name": null,
    "short_name": null,
    "official_name": null
  },
  {
    "country": "US",
    "state_abbr": "TN",
    "state_name": "Tennessee",
    "name": "University of Tennessee",
    "osm_type": "way",
    "osm_id": 1085257265,
    "admin_level": "10",
    "level_name": "Neighborhoods/Hamlets",
    "wikidata": null,
    "fips": null,
    "alt_name": null,
    "short_name": null,
    "official_name": null
  },
  {
    "country": "US",
    "state_abbr": "TN",
    "state_name": "Tennessee",
    "name": "University of Tennessee",
    "osm_type": "way",
    "osm_id": 1085257266,
    "admin_level": "10",
    "level_name": "Neighborhoods/Hamlets",
    "wikidata": null,
    "fips": null,
    "alt_name": null,
    "short_name": null,
    "official_name": null
  },
  {
    "country": "US",
    "state_abbr": "TN",
    "state_name": "Tennessee",
    "name": "University of Tennessee",
    "osm_type": "way",
    "osm_id": 1085257267,
    "admin_level": "10",
    "level_name": "Neighborhoods/Hamlets",
    "wikidata": null,
    "fips": null,
    "alt_name": null,
    "short_name": null,
    "official_name": null
  },
  {
    "country": "US",
    "state_abbr": "TN",
    "state_name": "Tennessee",
    "name": "University of Tennessee",
    "osm_type": "way",
    "osm_id": 1085679814,
    "admin_level": "10",
    "level_name": "Neighborhoods/Hamlets",
    "wikidata": null,
    "fips": null,
    "alt_name": null,
    "short_name": null,
    "official_name": null
  },
  {
    "country": "US",
    "state_abbr": "TN",
    "state_name": "Tennessee",
    "name": "University of Tennessee",
    "osm_type": "way",
    "osm_id": 1097824428,
    "admin_level": "10",
    "level_name": "Neighborhoods/Hamlets",
    "wikidata": null,
    "fips": null,
    "alt_name": null,
    "short_name": null,
    "official_name": null
  },
  {
    "country": "US",
    "state_abbr": "TN",
    "state_name": "Tennessee",
    "name": "Parkridge",
    "osm_type": "way",
    "osm_id": 1258056637,
    "admin_level": "10",
    "level_name": "Neighborhoods/Hamlets",
    "wikidata": null,
    "fips": null,
    "alt_name": null,
    "short_name": null,
    "official_name": null
  },
  {
    "country": "US",
    "state_abbr": "TN",
    "state_name": "Tennessee",
    "name": "University of Tennessee",
    "osm_type": "way",
    "osm_id": 1289174468,
    "admin_level": "10",
    "level_name": "Neighborhoods/Hamlets",
    "wikidata": null,
    "fips": null,
    "alt_name": null,
    "short_name": null,
    "official_name": null
  },
  {
    "country": "US",
    "state_abbr": "TN",
    "state_name": "Tennessee",
    "name": "University of Tennessee",
    "osm_type": "way",
    "osm_id": 1343500797,
    "admin_level": "10",
    "level_name": "Neighborhoods/Hamlets",
    "wikidata": null,
    "fips": null,
    "alt_name": null,
    "short_name": null,
    "official_name": null
  },
  {
    "country": "US",
    "state_abbr": "TN",
    "state_name": "Tennessee",
    "name": "University of Tennessee",
    "osm_type": "way",
    "osm_id": 1347195746,
    "admin_level": "10",
    "level_name": "Neighborhoods/Hamlets",
    "wikidata": null,
    "fips": null,
    "alt_name": null,
    "short_name": null,
    "official_name": null
  },
  {
    "country": "US",
    "state_abbr": "TN",
    "state_name": "Tennessee",
    "name": "Sequoyah Hills",
    "osm_type": "relation",
    "osm_id": 9245001,
    "admin_level": "10",
    "level_name": "Neighborhoods/Hamlets",
    "wikidata": "Q7452576",
    "fips": null,
    "alt_name": null,
    "short_name": null,
    "official_name": null
  },
  {
    "country": "US",
    "state_abbr": "TN",
    "state_name": "Tennessee",
    "name": "Speedway Terrace",
    "osm_type": "relation",
    "osm_id": 10912172,
    "admin_level": "10",
    "level_name": "Neighborhoods/Hamlets",
    "wikidata": "Q85802565",
    "fips": null,
    "alt_name": null,
    "short_name": null,
    "official_name": null
  },
  {
    "country": "US",
    "state_abbr": "TN",
    "state_name": "Tennessee",
    "name": "Westwood",
    "osm_type": "relation",
    "osm_id": 10979031,
    "admin_level": "10",
    "level_name": "Neighborhoods/Hamlets",
    "wikidata": "Q7989845",
    "fips": null,
    "alt_name": null,
    "short_name": null,
    "official_name": null
  },
  {
    "country": "US",
    "state_abbr": "TN",
    "state_name": "Tennessee",
    "name": "Cedar Bluff",
    "osm_type": "relation",
    "osm_id": 12532831,
    "admin_level": "10",
    "level_name": "Neighborhoods/Hamlets",
    "wikidata": "Q105102526",
    "fips": null,
    "alt_name": null,
    "short_name": null,
    "official_name": null
  },
  {
    "country": "US",
    "state_abbr": "TN",
    "state_name": "Tennessee",
    "name": "West Hills",
    "osm_type": "relation",
    "osm_id": 12533044,
    "admin_level": "10",
    "level_name": "Neighborhoods/Hamlets",
    "wikidata": null,
    "fips": null,
    "alt_name": null,
    "short_name": null,
    "official_name": null
  },
  {
    "country": "US",
    "state_abbr": "TN",
    "state_name": "Tennessee",
    "name": "Westwood",
    "osm_type": "relation",
    "osm_id": 12824496,
    "admin_level": "10",
    "level_name": "Neighborhoods/Hamlets",
    "wikidata": null,
    "fips": null,
    "alt_name": null,
    "short_name": null,
    "official_name": null
  },
  {
    "country": "US",
    "state_abbr": "TN",
    "state_name": "Tennessee",
    "name": "Sutherland Heights",
    "osm_type": "relation",
    "osm_id": 12824497,
    "admin_level": "10",
    "level_name": "Neighborhoods/Hamlets",
    "wikidata": null,
    "fips": null,
    "alt_name": null,
    "short_name": null,
    "official_name": null
  },
  {
    "country": "US",
    "state_abbr": "TN",
    "state_name": "Tennessee",
    "name": "Parkridge",
    "osm_type": "relation",
    "osm_id": 12870456,
    "admin_level": "10",
    "level_name": "Neighborhoods/Hamlets",
    "wikidata": "Q7138624",
    "fips": null,
    "alt_name": null,
    "short_name": null,
    "official_name": null
  },
  {
    "country": "US",
    "state_abbr": "TN",
    "state_name": "Tennessee",
    "name": "Holston Hills",
    "osm_type": "relation",
    "osm_id": 12870457,
    "admin_level": "10",
    "level_name": "Neighborhoods/Hamlets",
    "wikidata": null,
    "fips": null,
    "alt_name": null,
    "short_name": null,
    "official_name": null
  },
  {
    "country": "US",
    "state_abbr": "TN",
    "state_name": "Tennessee",
    "name": "Burlington",
    "osm_type": "relation",
    "osm_id": 12870458,
    "admin_level": "10",
    "level_name": "Neighborhoods/Hamlets",
    "wikidata": null,
    "fips": null,
    "alt_name": null,
    "short_name": null,
    "official_name": null
  },
  {
    "country": "US",
    "state_abbr": "TN",
    "state_name": "Tennessee",
    "name": "Chilhowee Park",
    "osm_type": "relation",
    "osm_id": 12870459,
    "admin_level": "10",
    "level_name": "Neighborhoods/Hamlets",
    "wikidata": null,
    "fips": null,
    "alt_name": null,
    "short_name": null,
    "official_name": null
  },
  {
    "country": "US",
    "state_abbr": "TN",
    "state_name": "Tennessee",
    "name": "Chilhowee Hills",
    "osm_type": "relation",
    "osm_id": 12870460,
    "admin_level": "10",
    "level_name": "Neighborhoods/Hamlets",
    "wikidata": null,
    "fips": null,
    "alt_name": null,
    "short_name": null,
    "official_name": null
  },
  {
    "country": "US",
    "state_abbr": "TN",
    "state_name": "Tennessee",
    "name": "John Sevier",
    "osm_type": "relation",
    "osm_id": 12870543,
    "admin_level": "10",
    "level_name": "Neighborhoods/Hamlets",
    "wikidata": null,
    "fips": null,
    "alt_name": null,
    "short_name": null,
    "official_name": null
  },
  {
    "country": "US",
    "state_abbr": "TN",
    "state_name": "Tennessee",
    "name": "Fourth and Gill",
    "osm_type": "relation",
    "osm_id": 12874787,
    "admin_level": "10",
    "level_name": "Neighborhoods/Hamlets",
    "wikidata": null,
    "fips": null,
    "alt_name": null,
    "short_name": null,
    "official_name": null
  },
  {
    "country": "US",
    "state_abbr": "TN",
    "state_name": "Tennessee",
    "name": "University of Tennessee",
    "osm_type": "relation",
    "osm_id": 12878230,
    "admin_level": "10",
    "level_name": "Neighborhoods/Hamlets",
    "wikidata": null,
    "fips": null,
    "alt_name": null,
    "short_name": null,
    "official_name": null
  },
  {
    "country": "US",
    "state_abbr": "TN",
    "state_name": "Tennessee",
    "name": "Karns",
    "osm_type": "relation",
    "osm_id": 13155732,
    "admin_level": "10",
    "level_name": "Neighborhoods/Hamlets",
    "wikidata": null,
    "fips": null,
    "alt_name": null,
    "short_name": null,
    "official_name": null
  },
  {
    "country": "US",
    "state_abbr": "TN",
    "state_name": "Tennessee",
    "name": "Bearden",
    "osm_type": "relation",
    "osm_id": 13689972,
    "admin_level": "10",
    "level_name": "Neighborhoods/Hamlets",
    "wikidata": "Q4876658",
    "fips": null,
    "alt_name": null,
    "short_name": null,
    "official_name": null
  },
  {
    "country": "US",
    "state_abbr": "TN",
    "state_name": "Tennessee",
    "name": "Marble City",
    "osm_type": "relation",
    "osm_id": 13689973,
    "admin_level": "10",
    "level_name": "Neighborhoods/Hamlets",
    "wikidata": null,
    "fips": null,
    "alt_name": null,
    "short_name": null,
    "official_name": null
  }
]